[
  {
    "einleitung": "Das Diagramm zeigt die Graphen der Angebots- und Nachfragefunktion. Bestimmen Sie",
    "fragen": [
      "den Mindestangebotspreis.",
      "den Höchstpreis.",
      "die Sättigungsmenge.",
      "die Gleichgewichtsmenge.",
      "den Gleichgewichtspreis."
    ],
    "antworten": [
      "{1:NUMERICAL:=2,01:0,25}",
      "{1:NUMERICAL:=20,63:0,25}",
      "{1:NUMERICAL:=25,9497:0,5}",
      "{1:NUMERICAL:=13,3707:0,5}",
      "{1:NUMERICAL:=10,0003:0,25}"
    ],
    "visual": {
      "type": "plot",
      "spec": {
        "type": "market-equilibrium",
        "params": {
          "supply": {
            "type": "quadratic",
            "a": 0.034,
            "b": 0.143,
            "c": 2.01
          },
          "demand": {
            "type": "linear",
            "a": -0.795,
            "b": 20.63
          },
          "eqX": 13.3707,
          "eqP": 10.0003,
          "satX": 25.9497,
          "maxX": 28.545,
          "maxY": 23.106
        },
        "layout": {
          "title": "Angebots- und Nachfragefunktion",
          "xaxis": {
            "title": "Menge x"
          },
          "yaxis": {
            "title": "Preis p"
          }
        },
        "width": 900,
        "height": 520,
        "scale": 1
      }
    }
  },
  {
    "einleitung": "Das Diagramm zeigt die Graphen der Angebots- und Nachfragefunktion. Bestimmen Sie",
    "fragen": [
      "den Mindestangebotspreis.",
      "den Höchstpreis.",
      "die Sättigungsmenge.",
      "die Gleichgewichtsmenge.",
      "den Gleichgewichtspreis."
    ],
    "antworten": [
      "{1:NUMERICAL:=1,5:0,25}",
      "{1:NUMERICAL:=7,91:0,25}",
      "{1:NUMERICAL:=10,8654:0,5}",
      "{1:NUMERICAL:=4,7314:0,5}",
      "{1:NUMERICAL:=3,5655:0,25}"
    ],
    "visual": {
      "type": "plot",
      "spec": {
        "type": "market-equilibrium",
        "params": {
          "supply": {
            "type": "quadratic",
            "a": 0.024,
            "b": 0.323,
            "c": 1.5
          },
          "demand": {
            "type": "exp",
            "A": 13.12,
            "rate": 0.085,
            "c": -5.21
          },
          "eqX": 4.7314,
          "eqP": 3.5655,
          "satX": 10.8654,
          "maxX": 12.0,
          "maxY": 8.859
        },
        "layout": {
          "title": "Angebots- und Nachfragefunktion",
          "xaxis": {
            "title": "Menge x"
          },
          "yaxis": {
            "title": "Preis p"
          }
        },
        "width": 900,
        "height": 520,
        "scale": 1
      }
    }
  },
  {
    "einleitung": "Das Diagramm zeigt die Graphen der Angebots- und Nachfragefunktion. Bestimmen Sie",
    "fragen": [
      "den Mindestangebotspreis.",
      "den Höchstpreis.",
      "die Sättigungsmenge.",
      "die Gleichgewichtsmenge.",
      "den Gleichgewichtspreis."
    ],
    "antworten": [
      "{1:NUMERICAL:=5,47:0,25}",
      "{1:NUMERICAL:=32,1:0,25}",
      "{1:NUMERICAL:=18,0562:0,5}",
      "{1:NUMERICAL:=5,1439:0,5}",
      "{1:NUMERICAL:=17,0967:0,25}"
    ],
    "visual": {
      "type": "plot",
      "spec": {
        "type": "market-equilibrium",
        "params": {
          "supply": {
            "type": "exp",
            "A": -19.59,
            "rate": 0.175,
            "c": 25.06
          },
          "demand": {
            "type": "exp",
            "A": 39.46,
            "rate": 0.093,
            "c": -7.36
          },
          "eqX": 5.1439,
          "eqP": 17.0967,
          "satX": 18.0562,
          "maxX": 19.862,
          "maxY": 35.952
        },
        "layout": {
          "title": "Angebots- und Nachfragefunktion",
          "xaxis": {
            "title": "Menge x"
          },
          "yaxis": {
            "title": "Preis p"
          }
        },
        "width": 900,
        "height": 520,
        "scale": 1
      }
    }
  },
  {
    "einleitung": "Das Diagramm zeigt die Graphen der Angebots- und Nachfragefunktion. Bestimmen Sie",
    "fragen": [
      "den Mindestangebotspreis.",
      "den Höchstpreis.",
      "die Sättigungsmenge.",
      "die Gleichgewichtsmenge.",
      "den Gleichgewichtspreis."
    ],
    "antworten": [
      "{1:NUMERICAL:=8,37:0,25}",
      "{1:NUMERICAL:=34,52:0,25}",
      "{1:NUMERICAL:=32,8762:0,5}",
      "{1:NUMERICAL:=11,9026:0,5}",
      "{1:NUMERICAL:=22,0223:0,25}"
    ],
    "visual": {
      "type": "plot",
      "spec": {
        "type": "market-equilibrium",
        "params": {
          "supply": {
            "type": "linear",
            "a": 1.147,
            "b": 8.37
          },
          "demand": {
            "type": "linear",
            "a": -1.05,
            "b": 34.52
          },
          "eqX": 11.9026,
          "eqP": 22.0223,
          "satX": 32.8762,
          "maxX": 36.164,
          "maxY": 38.662
        },
        "layout": {
          "title": "Angebots- und Nachfragefunktion",
          "xaxis": {
            "title": "Menge x"
          },
          "yaxis": {
            "title": "Preis p"
          }
        },
        "width": 900,
        "height": 520,
        "scale": 1
      }
    }
  },
  {
    "einleitung": "Das Diagramm zeigt die Graphen der Angebots- und Nachfragefunktion. Bestimmen Sie",
    "fragen": [
      "den Mindestangebotspreis.",
      "den Höchstpreis.",
      "die Sättigungsmenge.",
      "die Gleichgewichtsmenge.",
      "den Gleichgewichtspreis."
    ],
    "antworten": [
      "{1:NUMERICAL:=8,93:0,25}",
      "{1:NUMERICAL:=31,2:0,25}",
      "{1:NUMERICAL:=31,7128:0,5}",
      "{1:NUMERICAL:=12,3054:0,5}",
      "{1:NUMERICAL:=12,8315:0,25}"
    ],
    "visual": {
      "type": "plot",
      "spec": {
        "type": "market-equilibrium",
        "params": {
          "supply": {
            "type": "quadratic",
            "a": 0.01,
            "b": 0.194,
            "c": 8.93
          },
          "demand": {
            "type": "exp",
            "A": 38.34,
            "rate": 0.053,
            "c": -7.14
          },
          "eqX": 12.3054,
          "eqP": 12.8315,
          "satX": 31.7128,
          "maxX": 34.884,
          "maxY": 34.944
        },
        "layout": {
          "title": "Angebots- und Nachfragefunktion",
          "xaxis": {
            "title": "Menge x"
          },
          "yaxis": {
            "title": "Preis p"
          }
        },
        "width": 900,
        "height": 520,
        "scale": 1
      }
    }
  },
  {
    "einleitung": "Das Diagramm zeigt die Graphen der Angebots- und Nachfragefunktion. Bestimmen Sie",
    "fragen": [
      "den Mindestangebotspreis.",
      "den Höchstpreis.",
      "die Sättigungsmenge.",
      "die Gleichgewichtsmenge.",
      "den Gleichgewichtspreis."
    ],
    "antworten": [
      "{1:NUMERICAL:=7,61:0,25}",
      "{1:NUMERICAL:=22,1:0,25}",
      "{1:NUMERICAL:=16,1161:0,5}",
      "{1:NUMERICAL:=5,7434:0,5}",
      "{1:NUMERICAL:=10,2414:0,25}"
    ],
    "visual": {
      "type": "plot",
      "spec": {
        "type": "market-equilibrium",
        "params": {
          "supply": {
            "type": "quadratic",
            "a": 0.05,
            "b": 0.171,
            "c": 7.61
          },
          "demand": {
            "type": "exp",
            "A": 28.2,
            "rate": 0.095,
            "c": -6.1
          },
          "eqX": 5.7434,
          "eqP": 10.2414,
          "satX": 16.1161,
          "maxX": 17.728,
          "maxY": 24.752
        },
        "layout": {
          "title": "Angebots- und Nachfragefunktion",
          "xaxis": {
            "title": "Menge x"
          },
          "yaxis": {
            "title": "Preis p"
          }
        },
        "width": 900,
        "height": 520,
        "scale": 1
      }
    }
  },
  {
    "einleitung": "Das Diagramm zeigt die Graphen der Angebots- und Nachfragefunktion. Bestimmen Sie",
    "fragen": [
      "den Mindestangebotspreis.",
      "den Höchstpreis.",
      "die Sättigungsmenge.",
      "die Gleichgewichtsmenge.",
      "den Gleichgewichtspreis."
    ],
    "antworten": [
      "{1:NUMERICAL:=1,6:0,25}",
      "{1:NUMERICAL:=16,7:0,25}",
      "{1:NUMERICAL:=26,8294:0,5}",
      "{1:NUMERICAL:=9,2162:0,5}",
      "{1:NUMERICAL:=8,0912:0,25}"
    ],
    "visual": {
      "type": "plot",
      "spec": {
        "type": "market-equilibrium",
        "params": {
          "supply": {
            "type": "quadratic",
            "a": 0.057,
            "b": 0.179,
            "c": 1.6
          },
          "demand": {
            "type": "exp",
            "A": 21.65,
            "rate": 0.055,
            "c": -4.95
          },
          "eqX": 9.2162,
          "eqP": 8.0912,
          "satX": 26.8294,
          "maxX": 29.512,
          "maxY": 18.704
        },
        "layout": {
          "title": "Angebots- und Nachfragefunktion",
          "xaxis": {
            "title": "Menge x"
          },
          "yaxis": {
            "title": "Preis p"
          }
        },
        "width": 900,
        "height": 520,
        "scale": 1
      }
    }
  },
  {
    "einleitung": "Das Diagramm zeigt die Graphen der Angebots- und Nachfragefunktion. Bestimmen Sie",
    "fragen": [
      "den Mindestangebotspreis.",
      "den Höchstpreis.",
      "die Sättigungsmenge.",
      "die Gleichgewichtsmenge.",
      "den Gleichgewichtspreis."
    ],
    "antworten": [
      "{1:NUMERICAL:=4,14:0,25}",
      "{1:NUMERICAL:=14:0,25}",
      "{1:NUMERICAL:=18,3651:0,5}",
      "{1:NUMERICAL:=3,9815:0,5}",
      "{1:NUMERICAL:=12,7401:0,25}"
    ],
    "visual": {
      "type": "plot",
      "spec": {
        "type": "market-equilibrium",
        "params": {
          "supply": {
            "type": "linear",
            "a": 2.16,
            "b": 4.14
          },
          "demand": {
            "type": "quadratic",
            "a": -0.031,
            "b": -0.193,
            "c": 14.0
          },
          "eqX": 3.9815,
          "eqP": 12.7401,
          "satX": 18.3651,
          "maxX": 20.202,
          "maxY": 15.68
        },
        "layout": {
          "title": "Angebots- und Nachfragefunktion",
          "xaxis": {
            "title": "Menge x"
          },
          "yaxis": {
            "title": "Preis p"
          }
        },
        "width": 900,
        "height": 520,
        "scale": 1
      }
    }
  },
  {
    "einleitung": "Das Diagramm zeigt die Graphen der Angebots- und Nachfragefunktion. Bestimmen Sie",
    "fragen": [
      "den Mindestangebotspreis.",
      "den Höchstpreis.",
      "die Sättigungsmenge.",
      "die Gleichgewichtsmenge.",
      "den Gleichgewichtspreis."
    ],
    "antworten": [
      "{1:NUMERICAL:=8,16:0,25}",
      "{1:NUMERICAL:=28,23:0,25}",
      "{1:NUMERICAL:=22,768:0,5}",
      "{1:NUMERICAL:=7,2921:0,5}",
      "{1:NUMERICAL:=14,5793:0,25}"
    ],
    "visual": {
      "type": "plot",
      "spec": {
        "type": "market-equilibrium",
        "params": {
          "supply": {
            "type": "exp",
            "A": -11.85,
            "rate": 0.107,
            "c": 20.01
          },
          "demand": {
            "type": "exp",
            "A": 37.06,
            "rate": 0.063,
            "c": -8.83
          },
          "eqX": 7.2921,
          "eqP": 14.5793,
          "satX": 22.768,
          "maxX": 25.045,
          "maxY": 31.618
        },
        "layout": {
          "title": "Angebots- und Nachfragefunktion",
          "xaxis": {
            "title": "Menge x"
          },
          "yaxis": {
            "title": "Preis p"
          }
        },
        "width": 900,
        "height": 520,
        "scale": 1
      }
    }
  },
  {
    "einleitung": "Das Diagramm zeigt die Graphen der Angebots- und Nachfragefunktion. Bestimmen Sie",
    "fragen": [
      "den Mindestangebotspreis.",
      "den Höchstpreis.",
      "die Sättigungsmenge.",
      "die Gleichgewichtsmenge.",
      "den Gleichgewichtspreis."
    ],
    "antworten": [
      "{1:NUMERICAL:=1,65:0,25}",
      "{1:NUMERICAL:=26,05:0,25}",
      "{1:NUMERICAL:=14,5531:0,5}",
      "{1:NUMERICAL:=10,6249:0,5}",
      "{1:NUMERICAL:=7,0315:0,25}"
    ],
    "visual": {
      "type": "plot",
      "spec": {
        "type": "market-equilibrium",
        "params": {
          "supply": {
            "type": "quadratic",
            "a": 0.02,
            "b": 0.294,
            "c": 1.65
          },
          "demand": {
            "type": "linear",
            "a": -1.79,
            "b": 26.05
          },
          "eqX": 10.6249,
          "eqP": 7.0315,
          "satX": 14.5531,
          "maxX": 16.008,
          "maxY": 29.176
        },
        "layout": {
          "title": "Angebots- und Nachfragefunktion",
          "xaxis": {
            "title": "Menge x"
          },
          "yaxis": {
            "title": "Preis p"
          }
        },
        "width": 900,
        "height": 520,
        "scale": 1
      }
    }
  },
  {
    "einleitung": "Das Diagramm zeigt die Graphen der Angebots- und Nachfragefunktion. Bestimmen Sie",
    "fragen": [
      "den Mindestangebotspreis.",
      "den Höchstpreis.",
      "die Sättigungsmenge.",
      "die Gleichgewichtsmenge.",
      "den Gleichgewichtspreis."
    ],
    "antworten": [
      "{1:NUMERICAL:=1,07:0,25}",
      "{1:NUMERICAL:=12,05:0,25}",
      "{1:NUMERICAL:=12,5825:0,5}",
      "{1:NUMERICAL:=6,6263:0,5}",
      "{1:NUMERICAL:=3,8775:0,25}"
    ],
    "visual": {
      "type": "plot",
      "spec": {
        "type": "market-equilibrium",
        "params": {
          "supply": {
            "type": "quadratic",
            "a": 0.041,
            "b": 0.152,
            "c": 1.07
          },
          "demand": {
            "type": "exp",
            "A": 16.75,
            "rate": 0.101,
            "c": -4.7
          },
          "eqX": 6.6263,
          "eqP": 3.8775,
          "satX": 12.5825,
          "maxX": 13.841,
          "maxY": 13.496
        },
        "layout": {
          "title": "Angebots- und Nachfragefunktion",
          "xaxis": {
            "title": "Menge x"
          },
          "yaxis": {
            "title": "Preis p"
          }
        },
        "width": 900,
        "height": 520,
        "scale": 1
      }
    }
  },
  {
    "einleitung": "Das Diagramm zeigt die Graphen der Angebots- und Nachfragefunktion. Bestimmen Sie",
    "fragen": [
      "den Mindestangebotspreis.",
      "den Höchstpreis.",
      "die Sättigungsmenge.",
      "die Gleichgewichtsmenge.",
      "den Gleichgewichtspreis."
    ],
    "antworten": [
      "{1:NUMERICAL:=8,12:0,25}",
      "{1:NUMERICAL:=20,67:0,25}",
      "{1:NUMERICAL:=14,7667:0,5}",
      "{1:NUMERICAL:=6,9224:0,5}",
      "{1:NUMERICAL:=15,9216:0,25}"
    ],
    "visual": {
      "type": "plot",
      "spec": {
        "type": "market-equilibrium",
        "params": {
          "supply": {
            "type": "linear",
            "a": 1.127,
            "b": 8.12
          },
          "demand": {
            "type": "quadratic",
            "a": -0.091,
            "b": -0.056,
            "c": 20.67
          },
          "eqX": 6.9224,
          "eqP": 15.9216,
          "satX": 14.7667,
          "maxX": 16.243,
          "maxY": 23.15
        },
        "layout": {
          "title": "Angebots- und Nachfragefunktion",
          "xaxis": {
            "title": "Menge x"
          },
          "yaxis": {
            "title": "Preis p"
          }
        },
        "width": 900,
        "height": 520,
        "scale": 1
      }
    }
  },
  {
    "einleitung": "Das Diagramm zeigt die Graphen der Angebots- und Nachfragefunktion. Bestimmen Sie",
    "fragen": [
      "den Mindestangebotspreis.",
      "den Höchstpreis.",
      "die Sättigungsmenge.",
      "die Gleichgewichtsmenge.",
      "den Gleichgewichtspreis."
    ],
    "antworten": [
      "{1:NUMERICAL:=2,69:0,25}",
      "{1:NUMERICAL:=7,39:0,25}",
      "{1:NUMERICAL:=16,3883:0,5}",
      "{1:NUMERICAL:=7,7028:0,5}",
      "{1:NUMERICAL:=5,4553:0,25}"
    ],
    "visual": {
      "type": "plot",
      "spec": {
        "type": "market-equilibrium",
        "params": {
          "supply": {
            "type": "linear",
            "a": 0.359,
            "b": 2.69
          },
          "demand": {
            "type": "quadratic",
            "a": -0.023,
            "b": -0.074,
            "c": 7.39
          },
          "eqX": 7.7028,
          "eqP": 5.4553,
          "satX": 16.3883,
          "maxX": 18.027,
          "maxY": 8.277
        },
        "layout": {
          "title": "Angebots- und Nachfragefunktion",
          "xaxis": {
            "title": "Menge x"
          },
          "yaxis": {
            "title": "Preis p"
          }
        },
        "width": 900,
        "height": 520,
        "scale": 1
      }
    }
  },
  {
    "einleitung": "Das Diagramm zeigt die Graphen der Angebots- und Nachfragefunktion. Bestimmen Sie",
    "fragen": [
      "den Mindestangebotspreis.",
      "den Höchstpreis.",
      "die Sättigungsmenge.",
      "die Gleichgewichtsmenge.",
      "den Gleichgewichtspreis."
    ],
    "antworten": [
      "{1:NUMERICAL:=9,07:0,25}",
      "{1:NUMERICAL:=29,54:0,25}",
      "{1:NUMERICAL:=31,741:0,5}",
      "{1:NUMERICAL:=4,5018:0,5}",
      "{1:NUMERICAL:=18,0736:0,25}"
    ],
    "visual": {
      "type": "plot",
      "spec": {
        "type": "market-equilibrium",
        "params": {
          "supply": {
            "type": "linear",
            "a": 2.0,
            "b": 9.07
          },
          "demand": {
            "type": "exp",
            "A": 30.67,
            "rate": 0.104,
            "c": -1.13
          },
          "eqX": 4.5018,
          "eqP": 18.0736,
          "satX": 31.741,
          "maxX": 34.915,
          "maxY": 33.085
        },
        "layout": {
          "title": "Angebots- und Nachfragefunktion",
          "xaxis": {
            "title": "Menge x"
          },
          "yaxis": {
            "title": "Preis p"
          }
        },
        "width": 900,
        "height": 520,
        "scale": 1
      }
    }
  },
  {
    "einleitung": "Das Diagramm zeigt die Graphen der Angebots- und Nachfragefunktion. Bestimmen Sie",
    "fragen": [
      "den Mindestangebotspreis.",
      "den Höchstpreis.",
      "die Sättigungsmenge.",
      "die Gleichgewichtsmenge.",
      "den Gleichgewichtspreis."
    ],
    "antworten": [
      "{1:NUMERICAL:=7,47:0,25}",
      "{1:NUMERICAL:=17,89:0,25}",
      "{1:NUMERICAL:=7,1963:0,5}",
      "{1:NUMERICAL:=3,171:0,5}",
      "{1:NUMERICAL:=10,0068:0,25}"
    ],
    "visual": {
      "type": "plot",
      "spec": {
        "type": "market-equilibrium",
        "params": {
          "supply": {
            "type": "linear",
            "a": 0.8,
            "b": 7.47
          },
          "demand": {
            "type": "linear",
            "a": -2.486,
            "b": 17.89
          },
          "eqX": 3.171,
          "eqP": 10.0068,
          "satX": 7.1963,
          "maxX": 12.0,
          "maxY": 20.037
        },
        "layout": {
          "title": "Angebots- und Nachfragefunktion",
          "xaxis": {
            "title": "Menge x"
          },
          "yaxis": {
            "title": "Preis p"
          }
        },
        "width": 900,
        "height": 520,
        "scale": 1
      }
    }
  },
  {
    "einleitung": "Das Diagramm zeigt die Graphen der Angebots- und Nachfragefunktion. Bestimmen Sie",
    "fragen": [
      "den Mindestangebotspreis.",
      "den Höchstpreis.",
      "die Sättigungsmenge.",
      "die Gleichgewichtsmenge.",
      "den Gleichgewichtspreis."
    ],
    "antworten": [
      "{1:NUMERICAL:=5,96:0,25}",
      "{1:NUMERICAL:=39,38:0,25}",
      "{1:NUMERICAL:=32,4033:0,5}",
      "{1:NUMERICAL:=15,8107:0,5}",
      "{1:NUMERICAL:=28,8223:0,25}"
    ],
    "visual": {
      "type": "plot",
      "spec": {
        "type": "market-equilibrium",
        "params": {
          "supply": {
            "type": "linear",
            "a": 1.446,
            "b": 5.96
          },
          "demand": {
            "type": "quadratic",
            "a": -0.033,
            "b": -0.146,
            "c": 39.38
          },
          "eqX": 15.8107,
          "eqP": 28.8223,
          "satX": 32.4033,
          "maxX": 35.644,
          "maxY": 44.106
        },
        "layout": {
          "title": "Angebots- und Nachfragefunktion",
          "xaxis": {
            "title": "Menge x"
          },
          "yaxis": {
            "title": "Preis p"
          }
        },
        "width": 900,
        "height": 520,
        "scale": 1
      }
    }
  },
  {
    "einleitung": "Das Diagramm zeigt die Graphen der Angebots- und Nachfragefunktion. Bestimmen Sie",
    "fragen": [
      "den Mindestangebotspreis.",
      "den Höchstpreis.",
      "die Sättigungsmenge.",
      "die Gleichgewichtsmenge.",
      "den Gleichgewichtspreis."
    ],
    "antworten": [
      "{1:NUMERICAL:=7,87:0,25}",
      "{1:NUMERICAL:=41,65:0,25}",
      "{1:NUMERICAL:=25,1054:0,5}",
      "{1:NUMERICAL:=16,1708:0,5}",
      "{1:NUMERICAL:=23,0579:0,25}"
    ],
    "visual": {
      "type": "plot",
      "spec": {
        "type": "market-equilibrium",
        "params": {
          "supply": {
            "type": "quadratic",
            "a": 0.054,
            "b": 0.066,
            "c": 7.87
          },
          "demand": {
            "type": "quadratic",
            "a": -0.057,
            "b": -0.228,
            "c": 41.65
          },
          "eqX": 16.1708,
          "eqP": 23.0579,
          "satX": 25.1054,
          "maxX": 27.616,
          "maxY": 46.648
        },
        "layout": {
          "title": "Angebots- und Nachfragefunktion",
          "xaxis": {
            "title": "Menge x"
          },
          "yaxis": {
            "title": "Preis p"
          }
        },
        "width": 900,
        "height": 520,
        "scale": 1
      }
    }
  },
  {
    "einleitung": "Das Diagramm zeigt die Graphen der Angebots- und Nachfragefunktion. Bestimmen Sie",
    "fragen": [
      "den Mindestangebotspreis.",
      "den Höchstpreis.",
      "die Sättigungsmenge.",
      "die Gleichgewichtsmenge.",
      "den Gleichgewichtspreis."
    ],
    "antworten": [
      "{1:NUMERICAL:=7,59:0,25}",
      "{1:NUMERICAL:=29,46:0,25}",
      "{1:NUMERICAL:=25,5286:0,5}",
      "{1:NUMERICAL:=5,497:0,5}",
      "{1:NUMERICAL:=23,1165:0,25}"
    ],
    "visual": {
      "type": "plot",
      "spec": {
        "type": "market-equilibrium",
        "params": {
          "supply": {
            "type": "exp",
            "A": -19.68,
            "rate": 0.283,
            "c": 27.27
          },
          "demand": {
            "type": "linear",
            "a": -1.154,
            "b": 29.46
          },
          "eqX": 5.497,
          "eqP": 23.1165,
          "satX": 25.5286,
          "maxX": 28.081,
          "maxY": 32.995
        },
        "layout": {
          "title": "Angebots- und Nachfragefunktion",
          "xaxis": {
            "title": "Menge x"
          },
          "yaxis": {
            "title": "Preis p"
          }
        },
        "width": 900,
        "height": 520,
        "scale": 1
      }
    }
  },
  {
    "einleitung": "Das Diagramm zeigt die Graphen der Angebots- und Nachfragefunktion. Bestimmen Sie",
    "fragen": [
      "den Mindestangebotspreis.",
      "den Höchstpreis.",
      "die Sättigungsmenge.",
      "die Gleichgewichtsmenge.",
      "den Gleichgewichtspreis."
    ],
    "antworten": [
      "{1:NUMERICAL:=5,22:0,25}",
      "{1:NUMERICAL:=23,29:0,25}",
      "{1:NUMERICAL:=6,9002:0,5}",
      "{1:NUMERICAL:=3,7525:0,5}",
      "{1:NUMERICAL:=6,4615:0,25}"
    ],
    "visual": {
      "type": "plot",
      "spec": {
        "type": "market-equilibrium",
        "params": {
          "supply": {
            "type": "quadratic",
            "a": 0.033,
            "b": 0.207,
            "c": 5.22
          },
          "demand": {
            "type": "exp",
            "A": 29.6,
            "rate": 0.224,
            "c": -6.31
          },
          "eqX": 3.7525,
          "eqP": 6.4615,
          "satX": 6.9002,
          "maxX": 12.0,
          "maxY": 26.085
        },
        "layout": {
          "title": "Angebots- und Nachfragefunktion",
          "xaxis": {
            "title": "Menge x"
          },
          "yaxis": {
            "title": "Preis p"
          }
        },
        "width": 900,
        "height": 520,
        "scale": 1
      }
    }
  },
  {
    "einleitung": "Das Diagramm zeigt die Graphen der Angebots- und Nachfragefunktion. Bestimmen Sie",
    "fragen": [
      "den Mindestangebotspreis.",
      "den Höchstpreis.",
      "die Sättigungsmenge.",
      "die Gleichgewichtsmenge.",
      "den Gleichgewichtspreis."
    ],
    "antworten": [
      "{1:NUMERICAL:=7,61:0,25}",
      "{1:NUMERICAL:=19,63:0,25}",
      "{1:NUMERICAL:=26:0,5}",
      "{1:NUMERICAL:=13,8136:0,5}",
      "{1:NUMERICAL:=13,5775:0,25}"
    ],
    "visual": {
      "type": "plot",
      "spec": {
        "type": "market-equilibrium",
        "params": {
          "supply": {
            "type": "linear",
            "a": 0.432,
            "b": 7.61
          },
          "demand": {
            "type": "quadratic",
            "a": -0.026,
            "b": -0.079,
            "c": 19.63
          },
          "eqX": 13.8136,
          "eqP": 13.5775,
          "satX": 26.0,
          "maxX": 28.6,
          "maxY": 21.986
        },
        "layout": {
          "title": "Angebots- und Nachfragefunktion",
          "xaxis": {
            "title": "Menge x"
          },
          "yaxis": {
            "title": "Preis p"
          }
        },
        "width": 900,
        "height": 520,
        "scale": 1
      }
    }
  }
]