[
  {
    "einleitung": "Berechne die Determinante der Matrix $$ A = \\begin{pmatrix} 0 & -4 & 0 \\\\ -4 & 1 & 7 \\\\ 9 & 1 & -4 \\end{pmatrix} $$",
    "fragen": [
      "$ \\det(A) = $"
    ],
    "antworten": [
      "{1:NUMERICAL:=-188:0}"
    ]
  },
  {
    "einleitung": "Berechne die Determinante der Matrix $$ A = \\begin{pmatrix} -8 & 9 & 6 \\\\ 3 & 3 & -7 \\\\ -1 & 7 & -8 \\end{pmatrix} $$",
    "fragen": [
      "$ \\det(A) = $"
    ],
    "antworten": [
      "{1:NUMERICAL:=223:0}"
    ]
  },
  {
    "einleitung": "Berechne die Determinante der Matrix $$ A = \\begin{pmatrix} -6 & 6 & -2 \\\\ -4 & -7 & 0 \\\\ -6 & 3 & 9 \\end{pmatrix} $$",
    "fragen": [
      "$ \\det(A) = $"
    ],
    "antworten": [
      "{1:NUMERICAL:=702:0}"
    ]
  },
  {
    "einleitung": "Berechne die Determinante der Matrix $$ A = \\begin{pmatrix} 2 & 2 & -3 \\\\ 6 & 5 & 8 \\\\ -8 & 7 & -1 \\end{pmatrix} $$",
    "fragen": [
      "$ \\det(A) = $"
    ],
    "antworten": [
      "{1:NUMERICAL:=-484:0}"
    ]
  },
  {
    "einleitung": "Berechne die Determinante der Matrix $$ A = \\begin{pmatrix} -4 & 9 & 8 \\\\ -7 & -5 & -2 \\\\ 7 & 8 & 1 \\end{pmatrix} $$",
    "fragen": [
      "$ \\det(A) = $"
    ],
    "antworten": [
      "{1:NUMERICAL:=-275:0}"
    ]
  },
  {
    "einleitung": "Berechne die Determinante der Matrix $$ A = \\begin{pmatrix} 3 & 5 & -2 \\\\ 5 & 1 & 5 \\\\ 2 & 4 & 0 \\end{pmatrix} $$",
    "fragen": [
      "$ \\det(A) = $"
    ],
    "antworten": [
      "{1:NUMERICAL:=-46:0}"
    ]
  },
  {
    "einleitung": "Berechne die Determinante der Matrix $$ A = \\begin{pmatrix} 6 & -9 & 6 \\\\ 2 & 1 & -5 \\\\ -8 & -2 & -1 \\end{pmatrix} $$",
    "fragen": [
      "$ \\det(A) = $"
    ],
    "antworten": [
      "{1:NUMERICAL:=-420:0}"
    ]
  },
  {
    "einleitung": "Berechne die Determinante der Matrix $$ A = \\begin{pmatrix} 1 & -4 & -4 \\\\ 9 & 5 & -5 \\\\ -4 & -6 & 0 \\end{pmatrix} $$",
    "fragen": [
      "$ \\det(A) = $"
    ],
    "antworten": [
      "{1:NUMERICAL:=26:0}"
    ]
  },
  {
    "einleitung": "Berechne die Determinante der Matrix $$ A = \\begin{pmatrix} 7 & -3 & -9 \\\\ 1 & -3 & 7 \\\\ 5 & -6 & 5 \\end{pmatrix} $$",
    "fragen": [
      "$ \\det(A) = $"
    ],
    "antworten": [
      "{1:NUMERICAL:=18:0}"
    ]
  },
  {
    "einleitung": "Berechne die Determinante der Matrix $$ A = \\begin{pmatrix} -4 & 0 & 5 \\\\ -9 & 0 & 0 \\\\ 3 & 7 & -8 \\end{pmatrix} $$",
    "fragen": [
      "$ \\det(A) = $"
    ],
    "antworten": [
      "{1:NUMERICAL:=-315:0}"
    ]
  },
  {
    "einleitung": "Berechne die Determinante der Matrix $$ A = \\begin{pmatrix} 3 & 2 & -3 \\\\ -7 & 5 & 0 \\\\ -3 & 4 & -6 \\end{pmatrix} $$",
    "fragen": [
      "$ \\det(A) = $"
    ],
    "antworten": [
      "{1:NUMERICAL:=-135:0}"
    ]
  },
  {
    "einleitung": "Berechne die Determinante der Matrix $$ A = \\begin{pmatrix} 0 & 3 & -5 \\\\ 8 & 1 & -3 \\\\ 5 & -1 & -8 \\end{pmatrix} $$",
    "fragen": [
      "$ \\det(A) = $"
    ],
    "antworten": [
      "{1:NUMERICAL:=212:0}"
    ]
  },
  {
    "einleitung": "Berechne die Determinante der Matrix $$ A = \\begin{pmatrix} 4 & -1 & 7 \\\\ -4 & 1 & -4 \\\\ 1 & 7 & -7 \\end{pmatrix} $$",
    "fragen": [
      "$ \\det(A) = $"
    ],
    "antworten": [
      "{1:NUMERICAL:=-87:0}"
    ]
  },
  {
    "einleitung": "Berechne die Determinante der Matrix $$ A = \\begin{pmatrix} -9 & -9 & 3 \\\\ -3 & -8 & -9 \\\\ -2 & -2 & 9 \\end{pmatrix} $$",
    "fragen": [
      "$ \\det(A) = $"
    ],
    "antworten": [
      "{1:NUMERICAL:=375:0}"
    ]
  },
  {
    "einleitung": "Berechne die Determinante der Matrix $$ A = \\begin{pmatrix} -6 & 8 & 0 \\\\ 4 & 5 & -4 \\\\ 1 & 9 & 1 \\end{pmatrix} $$",
    "fragen": [
      "$ \\det(A) = $"
    ],
    "antworten": [
      "{1:NUMERICAL:=-310:0}"
    ]
  },
  {
    "einleitung": "Berechne die Determinante der Matrix $$ A = \\begin{pmatrix} -4 & -6 & 8 \\\\ 7 & 1 & 0 \\\\ 6 & -4 & 4 \\end{pmatrix} $$",
    "fragen": [
      "$ \\det(A) = $"
    ],
    "antworten": [
      "{1:NUMERICAL:=-120:0}"
    ]
  },
  {
    "einleitung": "Berechne die Determinante der Matrix $$ A = \\begin{pmatrix} 4 & -2 & -5 \\\\ -3 & -7 & -4 \\\\ 2 & -1 & -4 \\end{pmatrix} $$",
    "fragen": [
      "$ \\det(A) = $"
    ],
    "antworten": [
      "{1:NUMERICAL:=51:0}"
    ]
  },
  {
    "einleitung": "Berechne die Determinante der Matrix $$ A = \\begin{pmatrix} -8 & 7 & -7 \\\\ 8 & -3 & -3 \\\\ 3 & -7 & 3 \\end{pmatrix} $$",
    "fragen": [
      "$ \\det(A) = $"
    ],
    "antworten": [
      "{1:NUMERICAL:=338:0}"
    ]
  },
  {
    "einleitung": "Berechne die Determinante der Matrix $$ A = \\begin{pmatrix} -4 & -5 & -9 \\\\ -3 & -1 & 3 \\\\ 6 & -5 & 2 \\end{pmatrix} $$",
    "fragen": [
      "$ \\det(A) = $"
    ],
    "antworten": [
      "{1:NUMERICAL:=-361:0}"
    ]
  },
  {
    "einleitung": "Berechne die Determinante der Matrix $$ A = \\begin{pmatrix} -7 & 5 & -7 \\\\ 5 & -6 & 6 \\\\ 7 & 8 & -7 \\end{pmatrix} $$",
    "fragen": [
      "$ \\det(A) = $"
    ],
    "antworten": [
      "{1:NUMERICAL:=-147:0}"
    ]
  }
]