<?xml version="1.0" encoding="UTF-8" standalone="yes"?>

<quiz>

<question type="category">
  <category>
    <text>Analysis_Wirtschaft_Ökonomische Funktionen/06 Steckbriefaufgaben/quadratischKennzahlen</text>
  </category>
  <info format="html">
    <text></text>
  </info>
  <idnumber></idnumber>
</question>

<question type="cloze">
  <name>
    <text>01 </text>
  </name>
  <questiontext format="html">
    <text><![CDATA[<p>Es liegen folgende Informationen vor:</p> <p>Die Gewinngrenze beträgt 9 ME.</p> <p>Die gewinnmaximale Menge beträgt 6 ME.</p> <p>Die Gewinne bei 5 ME betragen 40 GE.</p><p>Bestimmen Sie die quadratische Gewinnfunktion.<br>\( G(x)= \){1:NUMERICAL:=-5:0}\( x^2 \)+{1:NUMERICAL:=60:0}\( x \)+{1:NUMERICAL:=-135:0}</p>]]></text>
  </questiontext>
</question>

<question type="cloze">
  <name>
    <text>02 </text>
  </name>
  <questiontext format="html">
    <text><![CDATA[<p>Es liegen folgende Informationen vor:</p> <p>Die Gewinngrenze beträgt 7 ME.</p> <p>Die gewinnmaximale Menge beträgt 4,5 ME.</p> <p>Die Gewinne bei 4 ME betragen 6 GE.</p><p>Bestimmen Sie die quadratische Gewinnfunktion.<br>\( G(x)= \){1:NUMERICAL:=-1:0}\( x^2 \)+{1:NUMERICAL:=9:0}\( x \)+{1:NUMERICAL:=-14:0}</p>]]></text>
  </questiontext>
</question>

<question type="cloze">
  <name>
    <text>03 </text>
  </name>
  <questiontext format="html">
    <text><![CDATA[<p>Es liegen folgende Informationen vor:</p> <p>Die Gewinnschwelle beträgt 4 ME.</p> <p>Die gewinnmaximale Menge beträgt 5 ME.</p> <p>Die Fixkosten betragen 120 GE.</p><p>Bestimmen Sie die quadratische Gewinnfunktion.<br>\( G(x)= \){1:NUMERICAL:=-5:0}\( x^2 \)+{1:NUMERICAL:=50:0}\( x \)+{1:NUMERICAL:=-120:0}</p>]]></text>
  </questiontext>
</question>

<question type="cloze">
  <name>
    <text>04 </text>
  </name>
  <questiontext format="html">
    <text><![CDATA[<p>Es liegen folgende Informationen vor:</p> <p>Die Gewinnschwelle beträgt 3 ME.</p> <p>Die Gewinngrenze beträgt 9 ME.</p> <p>Die Gewinne bei 10 ME betragen -14 GE.</p><p>Bestimmen Sie die quadratische Gewinnfunktion.<br>\( G(x)= \){1:NUMERICAL:=-2:0}\( x^2 \)+{1:NUMERICAL:=24:0}\( x \)+{1:NUMERICAL:=-54:0}</p>]]></text>
  </questiontext>
</question>

<question type="cloze">
  <name>
    <text>05 </text>
  </name>
  <questiontext format="html">
    <text><![CDATA[<p>Es liegen folgende Informationen vor:</p> <p>Die Gewinngrenze beträgt 9 ME.</p> <p>Die gewinnmaximale Menge beträgt 6 ME.</p> <p>Die Fixkosten betragen 27 GE.</p><p>Bestimmen Sie die quadratische Gewinnfunktion.<br>\( G(x)= \){1:NUMERICAL:=-1:0}\( x^2 \)+{1:NUMERICAL:=12:0}\( x \)+{1:NUMERICAL:=-27:0}</p>]]></text>
  </questiontext>
</question>

<question type="cloze">
  <name>
    <text>06 </text>
  </name>
  <questiontext format="html">
    <text><![CDATA[<p>Es liegen folgende Informationen vor:</p> <p>Die Gewinngrenze beträgt 7 ME.</p> <p>Die gewinnmaximale Menge beträgt 6 ME.</p> <p>Die Fixkosten betragen 70 GE.</p><p>Bestimmen Sie die quadratische Gewinnfunktion.<br>\( G(x)= \){1:NUMERICAL:=-2:0}\( x^2 \)+{1:NUMERICAL:=24:0}\( x \)+{1:NUMERICAL:=-70:0}</p>]]></text>
  </questiontext>
</question>

<question type="cloze">
  <name>
    <text>07 </text>
  </name>
  <questiontext format="html">
    <text><![CDATA[<p>Es liegen folgende Informationen vor:</p> <p>Die Gewinnschwelle beträgt 3 ME.</p> <p>Die Gewinngrenze beträgt 6 ME.</p> <p>Die Gewinne bei 10 ME betragen -140 GE.</p><p>Bestimmen Sie die quadratische Gewinnfunktion.<br>\( G(x)= \){1:NUMERICAL:=-5:0}\( x^2 \)+{1:NUMERICAL:=45:0}\( x \)+{1:NUMERICAL:=-90:0}</p>]]></text>
  </questiontext>
</question>

<question type="cloze">
  <name>
    <text>08 </text>
  </name>
  <questiontext format="html">
    <text><![CDATA[<p>Es liegen folgende Informationen vor:</p> <p>Die Gewinngrenze beträgt 10 ME.</p> <p>Die gewinnmaximale Menge beträgt 6,5 ME.</p> <p>Die Gewinne bei 8 ME betragen 30 GE.</p><p>Bestimmen Sie die quadratische Gewinnfunktion.<br>\( G(x)= \){1:NUMERICAL:=-3:0}\( x^2 \)+{1:NUMERICAL:=39:0}\( x \)+{1:NUMERICAL:=-90:0}</p>]]></text>
  </questiontext>
</question>

<question type="cloze">
  <name>
    <text>09 </text>
  </name>
  <questiontext format="html">
    <text><![CDATA[<p>Es liegen folgende Informationen vor:</p> <p>Die Gewinngrenze beträgt 6 ME.</p> <p>Die gewinnmaximale Menge beträgt 5 ME.</p> <p>Die Fixkosten betragen 24 GE.</p><p>Bestimmen Sie die quadratische Gewinnfunktion.<br>\( G(x)= \){1:NUMERICAL:=-1:0}\( x^2 \)+{1:NUMERICAL:=10:0}\( x \)+{1:NUMERICAL:=-24:0}</p>]]></text>
  </questiontext>
</question>

<question type="cloze">
  <name>
    <text>10 </text>
  </name>
  <questiontext format="html">
    <text><![CDATA[<p>Es liegen folgende Informationen vor:</p> <p>Die Gewinngrenze beträgt 9 ME.</p> <p>Die gewinnmaximale Menge beträgt 6,5 ME.</p> <p>Die Fixkosten betragen 36 GE.</p><p>Bestimmen Sie die quadratische Gewinnfunktion.<br>\( G(x)= \){1:NUMERICAL:=-1:0}\( x^2 \)+{1:NUMERICAL:=13:0}\( x \)+{1:NUMERICAL:=-36:0}</p>]]></text>
  </questiontext>
</question>

<question type="cloze">
  <name>
    <text>11 </text>
  </name>
  <questiontext format="html">
    <text><![CDATA[<p>Es liegen folgende Informationen vor:</p> <p>Die Gewinnschwelle beträgt 4 ME.</p> <p>Die gewinnmaximale Menge beträgt 5 ME.</p> <p>Die Gewinne bei 7 ME betragen -6 GE.</p><p>Bestimmen Sie die quadratische Gewinnfunktion.<br>\( G(x)= \){1:NUMERICAL:=-2:0}\( x^2 \)+{1:NUMERICAL:=20:0}\( x \)+{1:NUMERICAL:=-48:0}</p>]]></text>
  </questiontext>
</question>

<question type="cloze">
  <name>
    <text>12 </text>
  </name>
  <questiontext format="html">
    <text><![CDATA[<p>Es liegen folgende Informationen vor:</p> <p>Die Gewinngrenze beträgt 6 ME.</p> <p>Die gewinnmaximale Menge beträgt 4,5 ME.</p> <p>Die Gewinne bei 4 ME betragen 10 GE.</p><p>Bestimmen Sie die quadratische Gewinnfunktion.<br>\( G(x)= \){1:NUMERICAL:=-5:0}\( x^2 \)+{1:NUMERICAL:=45:0}\( x \)+{1:NUMERICAL:=-90:0}</p>]]></text>
  </questiontext>
</question>

<question type="cloze">
  <name>
    <text>13 </text>
  </name>
  <questiontext format="html">
    <text><![CDATA[<p>Es liegen folgende Informationen vor:</p> <p>Die Gewinngrenze beträgt 7 ME.</p> <p>Die gewinnmaximale Menge beträgt 5 ME.</p> <p>Die Gewinne bei 1 ME betragen -60 GE.</p><p>Bestimmen Sie die quadratische Gewinnfunktion.<br>\( G(x)= \){1:NUMERICAL:=-5:0}\( x^2 \)+{1:NUMERICAL:=50:0}\( x \)+{1:NUMERICAL:=-105:0}</p>]]></text>
  </questiontext>
</question>

<question type="cloze">
  <name>
    <text>14 </text>
  </name>
  <questiontext format="html">
    <text><![CDATA[<p>Es liegen folgende Informationen vor:</p> <p>Die Gewinnschwelle beträgt 4 ME.</p> <p>Die gewinnmaximale Menge beträgt 5,5 ME.</p> <p>Die Gewinne bei 9 ME betragen -30 GE.</p><p>Bestimmen Sie die quadratische Gewinnfunktion.<br>\( G(x)= \){1:NUMERICAL:=-3:0}\( x^2 \)+{1:NUMERICAL:=33:0}\( x \)+{1:NUMERICAL:=-84:0}</p>]]></text>
  </questiontext>
</question>

<question type="cloze">
  <name>
    <text>15 </text>
  </name>
  <questiontext format="html">
    <text><![CDATA[<p>Es liegen folgende Informationen vor:</p> <p>Die Gewinnschwelle beträgt 5 ME.</p> <p>Die gewinnmaximale Menge beträgt 6 ME.</p> <p>Die Gewinne bei 4 ME betragen -3 GE.</p><p>Bestimmen Sie die quadratische Gewinnfunktion.<br>\( G(x)= \){1:NUMERICAL:=-1:0}\( x^2 \)+{1:NUMERICAL:=12:0}\( x \)+{1:NUMERICAL:=-35:0}</p>]]></text>
  </questiontext>
</question>

<question type="cloze">
  <name>
    <text>16 </text>
  </name>
  <questiontext format="html">
    <text><![CDATA[<p>Es liegen folgende Informationen vor:</p> <p>Die Gewinnschwelle beträgt 2 ME.</p> <p>Die Gewinngrenze beträgt 6 ME.</p> <p>Die Fixkosten betragen 24 GE.</p><p>Bestimmen Sie die quadratische Gewinnfunktion.<br>\( G(x)= \){1:NUMERICAL:=-2:0}\( x^2 \)+{1:NUMERICAL:=16:0}\( x \)+{1:NUMERICAL:=-24:0}</p>]]></text>
  </questiontext>
</question>

<question type="cloze">
  <name>
    <text>17 </text>
  </name>
  <questiontext format="html">
    <text><![CDATA[<p>Es liegen folgende Informationen vor:</p> <p>Die Gewinnschwelle beträgt 4 ME.</p> <p>Die Gewinngrenze beträgt 8 ME.</p> <p>Die Gewinne bei 9 ME betragen -20 GE.</p><p>Bestimmen Sie die quadratische Gewinnfunktion.<br>\( G(x)= \){1:NUMERICAL:=-4:0}\( x^2 \)+{1:NUMERICAL:=48:0}\( x \)+{1:NUMERICAL:=-128:0}</p>]]></text>
  </questiontext>
</question>

<question type="cloze">
  <name>
    <text>18 </text>
  </name>
  <questiontext format="html">
    <text><![CDATA[<p>Es liegen folgende Informationen vor:</p> <p>Die Gewinngrenze beträgt 10 ME.</p> <p>Die gewinnmaximale Menge beträgt 5,5 ME.</p> <p>Die Gewinne bei 5 ME betragen 80 GE.</p><p>Bestimmen Sie die quadratische Gewinnfunktion.<br>\( G(x)= \){1:NUMERICAL:=-4:0}\( x^2 \)+{1:NUMERICAL:=44:0}\( x \)+{1:NUMERICAL:=-40:0}</p>]]></text>
  </questiontext>
</question>

<question type="cloze">
  <name>
    <text>19 </text>
  </name>
  <questiontext format="html">
    <text><![CDATA[<p>Es liegen folgende Informationen vor:</p> <p>Die Gewinnschwelle beträgt 5 ME.</p> <p>Die gewinnmaximale Menge beträgt 7,5 ME.</p> <p>Die Fixkosten betragen 50 GE.</p><p>Bestimmen Sie die quadratische Gewinnfunktion.<br>\( G(x)= \){1:NUMERICAL:=-1:0}\( x^2 \)+{1:NUMERICAL:=15:0}\( x \)+{1:NUMERICAL:=-50:0}</p>]]></text>
  </questiontext>
</question>

<question type="cloze">
  <name>
    <text>20 </text>
  </name>
  <questiontext format="html">
    <text><![CDATA[<p>Es liegen folgende Informationen vor:</p> <p>Die Gewinngrenze beträgt 8 ME.</p> <p>Die gewinnmaximale Menge beträgt 5 ME.</p> <p>Die Gewinne bei 3 ME betragen 25 GE.</p><p>Bestimmen Sie die quadratische Gewinnfunktion.<br>\( G(x)= \){1:NUMERICAL:=-5:0}\( x^2 \)+{1:NUMERICAL:=50:0}\( x \)+{1:NUMERICAL:=-80:0}</p>]]></text>
  </questiontext>
</question>

</quiz>

