[
{
"einleitung":"Gegeben:</p> <p>\\( RZ = \\left(\\begin{matrix}7&5\\\\1&3\\\\8&9\\\\ \\end{matrix}\\right) \\)\\(;\\quad\\)\\( ZE = \\left(\\begin{matrix}2&4&9\\\\5&3&3\\\\ \\end{matrix}\\right) \\)\\(;\\quad\\)\\( RE = \\left(\\begin{matrix}39&43&78\\\\17&13&18\\\\61&59&99\\\\ \\end{matrix}\\right) \\)\\(;\\quad\\)\\( \\vec{m} = \\left(\\begin{matrix}6\\\\9\\\\9\\\\ \\end{matrix}\\right) \\)\\(;\\quad\\)\\( \\vec{k_R} = \\left(\\begin{matrix}5&7&2\\\\ \\end{matrix}\\right) \\)\\(;\\quad\\)\\( \\vec{k_Z} = \\left(\\begin{matrix}7&2\\\\ \\end{matrix}\\right) \\)\\(;\\quad\\)\\( \\vec{k_E} = \\left(\\begin{matrix}3&9&5\\\\ \\end{matrix}\\right) \\)\\(;\\quad\\)\\( K_{fix}=2600\\)\\(;\\quad\\)\\( \\vec{p} = \\left(\\begin{matrix}381&320&768\\\\ \\end{matrix}\\right) \\)",
"fragen":[
"Berechnen Sie den Vektor der variablen Stückkosten \\( \\vec{k_v} = \\left(\\begin{matrix}a&b&c\\\\ \\end{matrix}\\right) \\).",
"Berechnen Sie den Vektor der Stückdeckungsbeiträge \\( \\vec{db} = \\left(\\begin{matrix}a&b&c\\\\ \\end{matrix}\\right) \\).",
"Berechnen Sie die Rohstoffkosten.",
"Berechnen Sie die Fertigungskosten der ersten Produktionsstufe.",
"Berechnen Sie die Fertigungskosten der zweiten Produktionsstufe.",
"Berechnen Sie die gesamten Kosten.",
"Berechnen Sie den Erlös.",
"Berechnen Sie den Deckungsbeitrag.",
"Berechnen Sie den Gewinn."
],
"antworten":[
"\\( a= \\){1:NUMERICAL:=463:0}\\( b= \\){1:NUMERICAL:=467:0}\\( c= \\){1:NUMERICAL:=788:0}<br>",
"\\( a= \\){1:NUMERICAL:=-82:0}\\( b= \\){1:NUMERICAL:=-147:0}\\( c= \\){1:NUMERICAL:=-20:0}<br>",
"{1:NUMERICAL:=12858:0}",
"{1:NUMERICAL:=1071:0}",
"{1:NUMERICAL:=144:0}",
"{1:NUMERICAL:=16673:0}",
"{1:NUMERICAL:=12078:0}",
"{1:NUMERICAL:=-1995:0}",
"{1:NUMERICAL:=-4595:0}"
]
},
{
"einleitung":"Gegeben:</p> <p>\\( RZ = \\left(\\begin{matrix}6&2&7\\\\4&5&7\\\\ \\end{matrix}\\right) \\)\\(;\\quad\\)\\( ZE = \\left(\\begin{matrix}1&5&1&2\\\\5&7&7&6\\\\9&2&5&3\\\\ \\end{matrix}\\right) \\)\\(;\\quad\\)\\( RE = \\left(\\begin{matrix}79&58&55&45\\\\92&69&74&59\\\\ \\end{matrix}\\right) \\)\\(;\\quad\\)\\( \\vec{m} = \\left(\\begin{matrix}6\\\\7\\\\4\\\\5\\\\ \\end{matrix}\\right) \\)\\(;\\quad\\)\\( \\vec{k_R} = \\left(\\begin{matrix}7&1\\\\ \\end{matrix}\\right) \\)\\(;\\quad\\)\\( \\vec{k_Z} = \\left(\\begin{matrix}3&7&8\\\\ \\end{matrix}\\right) \\)\\(;\\quad\\)\\( \\vec{k_E} = \\left(\\begin{matrix}4&8&1&8\\\\ \\end{matrix}\\right) \\)\\(;\\quad\\)\\( K_{fix}=2600\\)\\(;\\quad\\)\\( \\vec{p} = \\left(\\begin{matrix}1155&762&682&467\\\\ \\end{matrix}\\right) \\)",
"fragen":[
"Berechnen Sie den Vektor der variablen Stückkosten \\( \\vec{k_v} = \\left(\\begin{matrix}a&b&c&d\\\\ \\end{matrix}\\right) \\).",
"Berechnen Sie den Vektor der Stückdeckungsbeiträge \\( \\vec{db} = \\left(\\begin{matrix}a&b&c&d\\\\ \\end{matrix}\\right) \\).",
"Berechnen Sie die Rohstoffkosten.",
"Berechnen Sie die Fertigungskosten der ersten Produktionsstufe.",
"Berechnen Sie die Fertigungskosten der zweiten Produktionsstufe.",
"Berechnen Sie die gesamten Kosten.",
"Berechnen Sie den Erlös.",
"Berechnen Sie den Deckungsbeitrag.",
"Berechnen Sie den Gewinn."
],
"antworten":[
"\\( a= \\){1:NUMERICAL:=759:0}\\( b= \\){1:NUMERICAL:=563:0}\\( c= \\){1:NUMERICAL:=552:0}\\( d= \\){1:NUMERICAL:=454:0}<br>",
"\\( a= \\){1:NUMERICAL:=396:0}\\( b= \\){1:NUMERICAL:=199:0}\\( c= \\){1:NUMERICAL:=130:0}\\( d= \\){1:NUMERICAL:=13:0}<br>",
"{1:NUMERICAL:=10901:0}",
"{1:NUMERICAL:=1948:0}",
"{1:NUMERICAL:=124:0}",
"{1:NUMERICAL:=15573:0}",
"{1:NUMERICAL:=17327:0}",
"{1:NUMERICAL:=4354:0}",
"{1:NUMERICAL:=1754:0}"
]
},
{
"einleitung":"Gegeben:</p> <p>\\( RZ = \\left(\\begin{matrix}6&4\\\\3&8\\\\ \\end{matrix}\\right) \\)\\(;\\quad\\)\\( ZE = \\left(\\begin{matrix}6&5&2\\\\9&9&8\\\\ \\end{matrix}\\right) \\)\\(;\\quad\\)\\( RE = \\left(\\begin{matrix}72&66&44\\\\90&87&70\\\\ \\end{matrix}\\right) \\)\\(;\\quad\\)\\( \\vec{m} = \\left(\\begin{matrix}1\\\\5\\\\2\\\\ \\end{matrix}\\right) \\)\\(;\\quad\\)\\( \\vec{k_R} = \\left(\\begin{matrix}4&2\\\\ \\end{matrix}\\right) \\)\\(;\\quad\\)\\( \\vec{k_Z} = \\left(\\begin{matrix}3&5\\\\ \\end{matrix}\\right) \\)\\(;\\quad\\)\\( \\vec{k_E} = \\left(\\begin{matrix}7&1&5\\\\ \\end{matrix}\\right) \\)\\(;\\quad\\)\\( K_{fix}=2700\\)\\(;\\quad\\)\\( \\vec{p} = \\left(\\begin{matrix}646&543&656\\\\ \\end{matrix}\\right) \\)",
"fragen":[
"Berechnen Sie den Vektor der variablen Stückkosten \\( \\vec{k_v} = \\left(\\begin{matrix}a&b&c\\\\ \\end{matrix}\\right) \\).",
"Berechnen Sie den Vektor der Stückdeckungsbeiträge \\( \\vec{db} = \\left(\\begin{matrix}a&b&c\\\\ \\end{matrix}\\right) \\).",
"Berechnen Sie die Rohstoffkosten.",
"Berechnen Sie die Fertigungskosten der ersten Produktionsstufe.",
"Berechnen Sie die Fertigungskosten der zweiten Produktionsstufe.",
"Berechnen Sie die gesamten Kosten.",
"Berechnen Sie den Erlös.",
"Berechnen Sie den Deckungsbeitrag.",
"Berechnen Sie den Gewinn."
],
"antworten":[
"\\( a= \\){1:NUMERICAL:=538:0}\\( b= \\){1:NUMERICAL:=499:0}\\( c= \\){1:NUMERICAL:=367:0}<br>",
"\\( a= \\){1:NUMERICAL:=108:0}\\( b= \\){1:NUMERICAL:=44:0}\\( c= \\){1:NUMERICAL:=289:0}<br>",
"{1:NUMERICAL:=3290:0}",
"{1:NUMERICAL:=455:0}",
"{1:NUMERICAL:=22:0}",
"{1:NUMERICAL:=6467:0}",
"{1:NUMERICAL:=4673:0}",
"{1:NUMERICAL:=906:0}",
"{1:NUMERICAL:=-1794:0}"
]
},
{
"einleitung":"Gegeben:</p> <p>\\( RZ = \\left(\\begin{matrix}8&6\\\\2&9\\\\3&6\\\\ \\end{matrix}\\right) \\)\\(;\\quad\\)\\( ZE = \\left(\\begin{matrix}2&8\\\\7&2\\\\ \\end{matrix}\\right) \\)\\(;\\quad\\)\\( RE = \\left(\\begin{matrix}58&76\\\\67&34\\\\48&36\\\\ \\end{matrix}\\right) \\)\\(;\\quad\\)\\( \\vec{m} = \\left(\\begin{matrix}8\\\\2\\\\ \\end{matrix}\\right) \\)\\(;\\quad\\)\\( \\vec{k_R} = \\left(\\begin{matrix}9&6&6\\\\ \\end{matrix}\\right) \\)\\(;\\quad\\)\\( \\vec{k_Z} = \\left(\\begin{matrix}5&4\\\\ \\end{matrix}\\right) \\)\\(;\\quad\\)\\( \\vec{k_E} = \\left(\\begin{matrix}2&5\\\\ \\end{matrix}\\right) \\)\\(;\\quad\\)\\( K_{fix}=2900\\)\\(;\\quad\\)\\( \\vec{p} = \\left(\\begin{matrix}1850&1012\\\\ \\end{matrix}\\right) \\)",
"fragen":[
"Berechnen Sie den Vektor der variablen Stückkosten \\( \\vec{k_v} = \\left(\\begin{matrix}a&b\\\\ \\end{matrix}\\right) \\).",
"Berechnen Sie den Vektor der Stückdeckungsbeiträge \\( \\vec{db} = \\left(\\begin{matrix}a&b\\\\ \\end{matrix}\\right) \\).",
"Berechnen Sie die Rohstoffkosten.",
"Berechnen Sie die Fertigungskosten der ersten Produktionsstufe.",
"Berechnen Sie die Fertigungskosten der zweiten Produktionsstufe.",
"Berechnen Sie die gesamten Kosten.",
"Berechnen Sie den Erlös.",
"Berechnen Sie den Deckungsbeitrag.",
"Berechnen Sie den Gewinn."
],
"antworten":[
"\\( a= \\){1:NUMERICAL:=1252:0}\\( b= \\){1:NUMERICAL:=1157:0}<br>",
"\\( a= \\){1:NUMERICAL:=598:0}\\( b= \\){1:NUMERICAL:=-145:0}<br>",
"{1:NUMERICAL:=11904:0}",
"{1:NUMERICAL:=400:0}",
"{1:NUMERICAL:=26:0}",
"{1:NUMERICAL:=15230:0}",
"{1:NUMERICAL:=16824:0}",
"{1:NUMERICAL:=4494:0}",
"{1:NUMERICAL:=1594:0}"
]
},
{
"einleitung":"Gegeben:</p> <p>\\( RZ = \\left(\\begin{matrix}9&8&3\\\\7&3&4\\\\3&1&9\\\\2&1&9\\\\ \\end{matrix}\\right) \\)\\(;\\quad\\)\\( ZE = \\left(\\begin{matrix}3&3&7&5\\\\8&4&9&8\\\\5&4&4&1\\\\ \\end{matrix}\\right) \\)\\(;\\quad\\)\\( RE = \\left(\\begin{matrix}106&71&147&112\\\\65&49&92&63\\\\62&49&66&32\\\\59&46&59&27\\\\ \\end{matrix}\\right) \\)\\(;\\quad\\)\\( \\vec{m} = \\left(\\begin{matrix}7\\\\8\\\\6\\\\7\\\\ \\end{matrix}\\right) \\)\\(;\\quad\\)\\( \\vec{k_R} = \\left(\\begin{matrix}8&7&1&6\\\\ \\end{matrix}\\right) \\)\\(;\\quad\\)\\( \\vec{k_Z} = \\left(\\begin{matrix}9&2&2\\\\ \\end{matrix}\\right) \\)\\(;\\quad\\)\\( \\vec{k_E} = \\left(\\begin{matrix}8&4&1&8\\\\ \\end{matrix}\\right) \\)\\(;\\quad\\)\\( K_{fix}=6300\\)\\(;\\quad\\)\\( \\vec{p} = \\left(\\begin{matrix}1676&1278&2116&1533\\\\ \\end{matrix}\\right) \\)",
"fragen":[
"Berechnen Sie den Vektor der variablen Stückkosten \\( \\vec{k_v} = \\left(\\begin{matrix}a&b&c&d\\\\ \\end{matrix}\\right) \\).",
"Berechnen Sie den Vektor der Stückdeckungsbeiträge \\( \\vec{db} = \\left(\\begin{matrix}a&b&c&d\\\\ \\end{matrix}\\right) \\).",
"Berechnen Sie die Rohstoffkosten.",
"Berechnen Sie die Fertigungskosten der ersten Produktionsstufe.",
"Berechnen Sie die Fertigungskosten der zweiten Produktionsstufe.",
"Berechnen Sie die gesamten Kosten.",
"Berechnen Sie den Erlös.",
"Berechnen Sie den Deckungsbeitrag.",
"Berechnen Sie den Gewinn."
],
"antworten":[
"\\( a= \\){1:NUMERICAL:=1780:0}\\( b= \\){1:NUMERICAL:=1283:0}\\( c= \\){1:NUMERICAL:=2330:0}\\( d= \\){1:NUMERICAL:=1602:0}<br>",
"\\( a= \\){1:NUMERICAL:=-104:0}\\( b= \\){1:NUMERICAL:=-5:0}\\( c= \\){1:NUMERICAL:=-214:0}\\( d= \\){1:NUMERICAL:=-69:0}<br>",
"{1:NUMERICAL:=46078:0}",
"{1:NUMERICAL:=1690:0}",
"{1:NUMERICAL:=150:0}",
"{1:NUMERICAL:=54218:0}",
"{1:NUMERICAL:=45383:0}",
"{1:NUMERICAL:=-2535:0}",
"{1:NUMERICAL:=-8835:0}"
]
},
{
"einleitung":"Gegeben:</p> <p>\\( RZ = \\left(\\begin{matrix}4&6&9\\\\8&1&5\\\\6&7&9\\\\5&1&5\\\\ \\end{matrix}\\right) \\)\\(;\\quad\\)\\( ZE = \\left(\\begin{matrix}9&5&7\\\\4&5&5\\\\6&7&1\\\\ \\end{matrix}\\right) \\)\\(;\\quad\\)\\( RE = \\left(\\begin{matrix}114&113&67\\\\106&80&66\\\\136&128&86\\\\79&65&45\\\\ \\end{matrix}\\right) \\)\\(;\\quad\\)\\( \\vec{m} = \\left(\\begin{matrix}8\\\\4\\\\3\\\\ \\end{matrix}\\right) \\)\\(;\\quad\\)\\( \\vec{k_R} = \\left(\\begin{matrix}5&5&3&8\\\\ \\end{matrix}\\right) \\)\\(;\\quad\\)\\( \\vec{k_Z} = \\left(\\begin{matrix}9&9&6\\\\ \\end{matrix}\\right) \\)\\(;\\quad\\)\\( \\vec{k_E} = \\left(\\begin{matrix}1&6&7\\\\ \\end{matrix}\\right) \\)\\(;\\quad\\)\\( K_{fix}=5100\\)\\(;\\quad\\)\\( \\vec{p} = \\left(\\begin{matrix}2634&1408&1220\\\\ \\end{matrix}\\right) \\)",
"fragen":[
"Berechnen Sie den Vektor der variablen Stückkosten \\( \\vec{k_v} = \\left(\\begin{matrix}a&b&c\\\\ \\end{matrix}\\right) \\).",
"Berechnen Sie den Vektor der Stückdeckungsbeiträge \\( \\vec{db} = \\left(\\begin{matrix}a&b&c\\\\ \\end{matrix}\\right) \\).",
"Berechnen Sie die Rohstoffkosten.",
"Berechnen Sie die Fertigungskosten der ersten Produktionsstufe.",
"Berechnen Sie die Fertigungskosten der zweiten Produktionsstufe.",
"Berechnen Sie die gesamten Kosten.",
"Berechnen Sie den Erlös.",
"Berechnen Sie den Deckungsbeitrag.",
"Berechnen Sie den Gewinn."
],
"antworten":[
"\\( a= \\){1:NUMERICAL:=2294:0}\\( b= \\){1:NUMERICAL:=2007:0}\\( c= \\){1:NUMERICAL:=1404:0}<br>",
"\\( a= \\){1:NUMERICAL:=340:0}\\( b= \\){1:NUMERICAL:=-599:0}\\( c= \\){1:NUMERICAL:=-184:0}<br>",
"{1:NUMERICAL:=28445:0}",
"{1:NUMERICAL:=2094:0}",
"{1:NUMERICAL:=53:0}",
"{1:NUMERICAL:=35692:0}",
"{1:NUMERICAL:=30364:0}",
"{1:NUMERICAL:=-228:0}",
"{1:NUMERICAL:=-5328:0}"
]
},
{
"einleitung":"Gegeben:</p> <p>\\( RZ = \\left(\\begin{matrix}2&7&3\\\\8&9&6\\\\6&9&9\\\\7&4&6\\\\ \\end{matrix}\\right) \\)\\(;\\quad\\)\\( ZE = \\left(\\begin{matrix}2&4&5&9\\\\9&1&8&3\\\\6&9&5&5\\\\ \\end{matrix}\\right) \\)\\(;\\quad\\)\\( RE = \\left(\\begin{matrix}85&42&81&54\\\\133&95&142&129\\\\147&114&147&126\\\\86&86&97&105\\\\ \\end{matrix}\\right) \\)\\(;\\quad\\)\\( \\vec{m} = \\left(\\begin{matrix}4\\\\6\\\\2\\\\8\\\\ \\end{matrix}\\right) \\)\\(;\\quad\\)\\( \\vec{k_R} = \\left(\\begin{matrix}9&9&3&8\\\\ \\end{matrix}\\right) \\)\\(;\\quad\\)\\( \\vec{k_Z} = \\left(\\begin{matrix}2&8&9\\\\ \\end{matrix}\\right) \\)\\(;\\quad\\)\\( \\vec{k_E} = \\left(\\begin{matrix}8&7&2&6\\\\ \\end{matrix}\\right) \\)\\(;\\quad\\)\\( K_{fix}=7100\\)\\(;\\quad\\)\\( \\vec{p} = \\left(\\begin{matrix}2150&1905&4439&1987\\\\ \\end{matrix}\\right) \\)",
"fragen":[
"Berechnen Sie den Vektor der variablen Stückkosten \\( \\vec{k_v} = \\left(\\begin{matrix}a&b&c&d\\\\ \\end{matrix}\\right) \\).",
"Berechnen Sie den Vektor der Stückdeckungsbeiträge \\( \\vec{db} = \\left(\\begin{matrix}a&b&c&d\\\\ \\end{matrix}\\right) \\).",
"Berechnen Sie die Rohstoffkosten.",
"Berechnen Sie die Fertigungskosten der ersten Produktionsstufe.",
"Berechnen Sie die Fertigungskosten der zweiten Produktionsstufe.",
"Berechnen Sie die gesamten Kosten.",
"Berechnen Sie den Erlös.",
"Berechnen Sie den Deckungsbeitrag.",
"Berechnen Sie den Gewinn."
],
"antworten":[
"\\( a= \\){1:NUMERICAL:=3229:0}\\( b= \\){1:NUMERICAL:=2367:0}\\( c= \\){1:NUMERICAL:=3345:0}\\( d= \\){1:NUMERICAL:=2958:0}<br>",
"\\( a= \\){1:NUMERICAL:=-1079:0}\\( b= \\){1:NUMERICAL:=-462:0}\\( c= \\){1:NUMERICAL:=1094:0}\\( d= \\){1:NUMERICAL:=-971:0}<br>",
"{1:NUMERICAL:=55310:0}",
"{1:NUMERICAL:=2036:0}",
"{1:NUMERICAL:=126:0}",
"{1:NUMERICAL:=64572:0}",
"{1:NUMERICAL:=44804:0}",
"{1:NUMERICAL:=-12668:0}",
"{1:NUMERICAL:=-19768:0}"
]
},
{
"einleitung":"Gegeben:</p> <p>\\( RZ = \\left(\\begin{matrix}1&6\\\\3&8\\\\2&8\\\\ \\end{matrix}\\right) \\)\\(;\\quad\\)\\( ZE = \\left(\\begin{matrix}9&3&4\\\\1&4&4\\\\ \\end{matrix}\\right) \\)\\(;\\quad\\)\\( RE = \\left(\\begin{matrix}15&27&28\\\\35&41&44\\\\26&38&40\\\\ \\end{matrix}\\right) \\)\\(;\\quad\\)\\( \\vec{m} = \\left(\\begin{matrix}5\\\\1\\\\3\\\\ \\end{matrix}\\right) \\)\\(;\\quad\\)\\( \\vec{k_R} = \\left(\\begin{matrix}9&6&2\\\\ \\end{matrix}\\right) \\)\\(;\\quad\\)\\( \\vec{k_Z} = \\left(\\begin{matrix}5&2\\\\ \\end{matrix}\\right) \\)\\(;\\quad\\)\\( \\vec{k_E} = \\left(\\begin{matrix}1&3&2\\\\ \\end{matrix}\\right) \\)\\(;\\quad\\)\\( K_{fix}=1000\\)\\(;\\quad\\)\\( \\vec{p} = \\left(\\begin{matrix}664&657&761\\\\ \\end{matrix}\\right) \\)",
"fragen":[
"Berechnen Sie den Vektor der variablen Stückkosten \\( \\vec{k_v} = \\left(\\begin{matrix}a&b&c\\\\ \\end{matrix}\\right) \\).",
"Berechnen Sie den Vektor der Stückdeckungsbeiträge \\( \\vec{db} = \\left(\\begin{matrix}a&b&c\\\\ \\end{matrix}\\right) \\).",
"Berechnen Sie die Rohstoffkosten.",
"Berechnen Sie die Fertigungskosten der ersten Produktionsstufe.",
"Berechnen Sie die Fertigungskosten der zweiten Produktionsstufe.",
"Berechnen Sie die gesamten Kosten.",
"Berechnen Sie den Erlös.",
"Berechnen Sie den Deckungsbeitrag.",
"Berechnen Sie den Gewinn."
],
"antworten":[
"\\( a= \\){1:NUMERICAL:=445:0}\\( b= \\){1:NUMERICAL:=591:0}\\( c= \\){1:NUMERICAL:=626:0}<br>",
"\\( a= \\){1:NUMERICAL:=219:0}\\( b= \\){1:NUMERICAL:=66:0}\\( c= \\){1:NUMERICAL:=135:0}<br>",
"{1:NUMERICAL:=4338:0}",
"{1:NUMERICAL:=342:0}",
"{1:NUMERICAL:=14:0}",
"{1:NUMERICAL:=5694:0}",
"{1:NUMERICAL:=6260:0}",
"{1:NUMERICAL:=1566:0}",
"{1:NUMERICAL:=566:0}"
]
},
{
"einleitung":"Gegeben:</p> <p>\\( RZ = \\left(\\begin{matrix}8&2&8\\\\6&5&9\\\\5&2&4\\\\3&8&8\\\\ \\end{matrix}\\right) \\)\\(;\\quad\\)\\( ZE = \\left(\\begin{matrix}4&5&5&2\\\\2&8&2&5\\\\6&4&3&9\\\\ \\end{matrix}\\right) \\)\\(;\\quad\\)\\( RE = \\left(\\begin{matrix}84&88&68&98\\\\88&106&67&118\\\\48&57&41&56\\\\76&111&55&118\\\\ \\end{matrix}\\right) \\)\\(;\\quad\\)\\( \\vec{m} = \\left(\\begin{matrix}1\\\\4\\\\3\\\\9\\\\ \\end{matrix}\\right) \\)\\(;\\quad\\)\\( \\vec{k_R} = \\left(\\begin{matrix}1&3&6&9\\\\ \\end{matrix}\\right) \\)\\(;\\quad\\)\\( \\vec{k_Z} = \\left(\\begin{matrix}9&8&9\\\\ \\end{matrix}\\right) \\)\\(;\\quad\\)\\( \\vec{k_E} = \\left(\\begin{matrix}5&6&8&3\\\\ \\end{matrix}\\right) \\)\\(;\\quad\\)\\( K_{fix}=11000\\)\\(;\\quad\\)\\( \\vec{p} = \\left(\\begin{matrix}990&1468&2152&1779\\\\ \\end{matrix}\\right) \\)",
"fragen":[
"Berechnen Sie den Vektor der variablen Stückkosten \\( \\vec{k_v} = \\left(\\begin{matrix}a&b&c&d\\\\ \\end{matrix}\\right) \\).",
"Berechnen Sie den Vektor der Stückdeckungsbeiträge \\( \\vec{db} = \\left(\\begin{matrix}a&b&c&d\\\\ \\end{matrix}\\right) \\).",
"Berechnen Sie die Rohstoffkosten.",
"Berechnen Sie die Fertigungskosten der ersten Produktionsstufe.",
"Berechnen Sie die Fertigungskosten der zweiten Produktionsstufe.",
"Berechnen Sie die gesamten Kosten.",
"Berechnen Sie den Erlös.",
"Berechnen Sie den Deckungsbeitrag.",
"Berechnen Sie den Gewinn."
],
"antworten":[
"\\( a= \\){1:NUMERICAL:=1431:0}\\( b= \\){1:NUMERICAL:=1898:0}\\( c= \\){1:NUMERICAL:=1106:0}\\( d= \\){1:NUMERICAL:=1992:0}<br>",
"\\( a= \\){1:NUMERICAL:=-441:0}\\( b= \\){1:NUMERICAL:=-430:0}\\( c= \\){1:NUMERICAL:=1046:0}\\( d= \\){1:NUMERICAL:=-213:0}<br>",
"{1:NUMERICAL:=27988:0}",
"{1:NUMERICAL:=2201:0}",
"{1:NUMERICAL:=80:0}",
"{1:NUMERICAL:=41269:0}",
"{1:NUMERICAL:=29329:0}",
"{1:NUMERICAL:=-940:0}",
"{1:NUMERICAL:=-11940:0}"
]
},
{
"einleitung":"Gegeben:</p> <p>\\( RZ = \\left(\\begin{matrix}7&8&1\\\\8&1&5\\\\ \\end{matrix}\\right) \\)\\(;\\quad\\)\\( ZE = \\left(\\begin{matrix}3&6&8\\\\1&8&5\\\\8&7&1\\\\ \\end{matrix}\\right) \\)\\(;\\quad\\)\\( RE = \\left(\\begin{matrix}37&113&97\\\\65&91&74\\\\ \\end{matrix}\\right) \\)\\(;\\quad\\)\\( \\vec{m} = \\left(\\begin{matrix}4\\\\5\\\\7\\\\ \\end{matrix}\\right) \\)\\(;\\quad\\)\\( \\vec{k_R} = \\left(\\begin{matrix}5&5\\\\ \\end{matrix}\\right) \\)\\(;\\quad\\)\\( \\vec{k_Z} = \\left(\\begin{matrix}1&6&2\\\\ \\end{matrix}\\right) \\)\\(;\\quad\\)\\( \\vec{k_E} = \\left(\\begin{matrix}7&3&6\\\\ \\end{matrix}\\right) \\)\\(;\\quad\\)\\( K_{fix}=3300\\)\\(;\\quad\\)\\( \\vec{p} = \\left(\\begin{matrix}990&917&1008\\\\ \\end{matrix}\\right) \\)",
"fragen":[
"Berechnen Sie den Vektor der variablen Stückkosten \\( \\vec{k_v} = \\left(\\begin{matrix}a&b&c\\\\ \\end{matrix}\\right) \\).",
"Berechnen Sie den Vektor der Stückdeckungsbeiträge \\( \\vec{db} = \\left(\\begin{matrix}a&b&c\\\\ \\end{matrix}\\right) \\).",
"Berechnen Sie die Rohstoffkosten.",
"Berechnen Sie die Fertigungskosten der ersten Produktionsstufe.",
"Berechnen Sie die Fertigungskosten der zweiten Produktionsstufe.",
"Berechnen Sie die gesamten Kosten.",
"Berechnen Sie den Erlös.",
"Berechnen Sie den Deckungsbeitrag.",
"Berechnen Sie den Gewinn."
],
"antworten":[
"\\( a= \\){1:NUMERICAL:=542:0}\\( b= \\){1:NUMERICAL:=1091:0}\\( c= \\){1:NUMERICAL:=901:0}<br>",
"\\( a= \\){1:NUMERICAL:=448:0}\\( b= \\){1:NUMERICAL:=-174:0}\\( c= \\){1:NUMERICAL:=107:0}<br>",
"{1:NUMERICAL:=13125:0}",
"{1:NUMERICAL:=720:0}",
"{1:NUMERICAL:=85:0}",
"{1:NUMERICAL:=17230:0}",
"{1:NUMERICAL:=15601:0}",
"{1:NUMERICAL:=1671:0}",
"{1:NUMERICAL:=-1629:0}"
]
},
{
"einleitung":"Gegeben:</p> <p>\\( RZ = \\left(\\begin{matrix}2&2&6\\\\1&7&9\\\\ \\end{matrix}\\right) \\)\\(;\\quad\\)\\( ZE = \\left(\\begin{matrix}5&4&7&3\\\\3&8&6&3\\\\7&6&1&8\\\\ \\end{matrix}\\right) \\)\\(;\\quad\\)\\( RE = \\left(\\begin{matrix}58&60&32&60\\\\89&114&58&96\\\\ \\end{matrix}\\right) \\)\\(;\\quad\\)\\( \\vec{m} = \\left(\\begin{matrix}7\\\\5\\\\6\\\\9\\\\ \\end{matrix}\\right) \\)\\(;\\quad\\)\\( \\vec{k_R} = \\left(\\begin{matrix}4&2\\\\ \\end{matrix}\\right) \\)\\(;\\quad\\)\\( \\vec{k_Z} = \\left(\\begin{matrix}2&8&4\\\\ \\end{matrix}\\right) \\)\\(;\\quad\\)\\( \\vec{k_E} = \\left(\\begin{matrix}6&3&8&1\\\\ \\end{matrix}\\right) \\)\\(;\\quad\\)\\( K_{fix}=3500\\)\\(;\\quad\\)\\( \\vec{p} = \\left(\\begin{matrix}653&1038&295&468\\\\ \\end{matrix}\\right) \\)",
"fragen":[
"Berechnen Sie den Vektor der variablen Stückkosten \\( \\vec{k_v} = \\left(\\begin{matrix}a&b&c&d\\\\ \\end{matrix}\\right) \\).",
"Berechnen Sie den Vektor der Stückdeckungsbeiträge \\( \\vec{db} = \\left(\\begin{matrix}a&b&c&d\\\\ \\end{matrix}\\right) \\).",
"Berechnen Sie die Rohstoffkosten.",
"Berechnen Sie die Fertigungskosten der ersten Produktionsstufe.",
"Berechnen Sie die Fertigungskosten der zweiten Produktionsstufe.",
"Berechnen Sie die gesamten Kosten.",
"Berechnen Sie den Erlös.",
"Berechnen Sie den Deckungsbeitrag.",
"Berechnen Sie den Gewinn."
],
"antworten":[
"\\( a= \\){1:NUMERICAL:=478:0}\\( b= \\){1:NUMERICAL:=567:0}\\( c= \\){1:NUMERICAL:=318:0}\\( d= \\){1:NUMERICAL:=495:0}<br>",
"\\( a= \\){1:NUMERICAL:=175:0}\\( b= \\){1:NUMERICAL:=471:0}\\( c= \\){1:NUMERICAL:=-23:0}\\( d= \\){1:NUMERICAL:=-27:0}<br>",
"{1:NUMERICAL:=10562:0}",
"{1:NUMERICAL:=1868:0}",
"{1:NUMERICAL:=114:0}",
"{1:NUMERICAL:=16044:0}",
"{1:NUMERICAL:=15743:0}",
"{1:NUMERICAL:=3199:0}",
"{1:NUMERICAL:=-301:0}"
]
},
{
"einleitung":"Gegeben:</p> <p>\\( RZ = \\left(\\begin{matrix}6&9&2&6\\\\4&4&7&2\\\\ \\end{matrix}\\right) \\)\\(;\\quad\\)\\( ZE = \\left(\\begin{matrix}5&3&2&9\\\\4&2&9&3\\\\6&1&5&7\\\\3&2&8&9\\\\ \\end{matrix}\\right) \\)\\(;\\quad\\)\\( RE = \\left(\\begin{matrix}96&50&151&149\\\\84&31&95&115\\\\ \\end{matrix}\\right) \\)\\(;\\quad\\)\\( \\vec{m} = \\left(\\begin{matrix}3\\\\6\\\\4\\\\9\\\\ \\end{matrix}\\right) \\)\\(;\\quad\\)\\( \\vec{k_R} = \\left(\\begin{matrix}1&5\\\\ \\end{matrix}\\right) \\)\\(;\\quad\\)\\( \\vec{k_Z} = \\left(\\begin{matrix}9&8&2&7\\\\ \\end{matrix}\\right) \\)\\(;\\quad\\)\\( \\vec{k_E} = \\left(\\begin{matrix}9&8&1&9\\\\ \\end{matrix}\\right) \\)\\(;\\quad\\)\\( K_{fix}=3600\\)\\(;\\quad\\)\\( \\vec{p} = \\left(\\begin{matrix}896&497&481&1533\\\\ \\end{matrix}\\right) \\)",
"fragen":[
"Berechnen Sie den Vektor der variablen Stückkosten \\( \\vec{k_v} = \\left(\\begin{matrix}a&b&c&d\\\\ \\end{matrix}\\right) \\).",
"Berechnen Sie den Vektor der Stückdeckungsbeiträge \\( \\vec{db} = \\left(\\begin{matrix}a&b&c&d\\\\ \\end{matrix}\\right) \\).",
"Berechnen Sie die Rohstoffkosten.",
"Berechnen Sie die Fertigungskosten der ersten Produktionsstufe.",
"Berechnen Sie die Fertigungskosten der zweiten Produktionsstufe.",
"Berechnen Sie die gesamten Kosten.",
"Berechnen Sie den Erlös.",
"Berechnen Sie den Deckungsbeitrag.",
"Berechnen Sie den Gewinn."
],
"antworten":[
"\\( a= \\){1:NUMERICAL:=635:0}\\( b= \\){1:NUMERICAL:=272:0}\\( c= \\){1:NUMERICAL:=783:0}\\( d= \\){1:NUMERICAL:=915:0}<br>",
"\\( a= \\){1:NUMERICAL:=261:0}\\( b= \\){1:NUMERICAL:=225:0}\\( c= \\){1:NUMERICAL:=-302:0}\\( d= \\){1:NUMERICAL:=618:0}<br>",
"{1:NUMERICAL:=11798:0}",
"{1:NUMERICAL:=2946:0}",
"{1:NUMERICAL:=160:0}",
"{1:NUMERICAL:=18504:0}",
"{1:NUMERICAL:=21391:0}",
"{1:NUMERICAL:=6487:0}",
"{1:NUMERICAL:=2887:0}"
]
},
{
"einleitung":"Gegeben:</p> <p>\\( RZ = \\left(\\begin{matrix}5&6&4&3\\\\7&2&3&7\\\\2&7&1&6\\\\9&2&2&8\\\\ \\end{matrix}\\right) \\)\\(;\\quad\\)\\( ZE = \\left(\\begin{matrix}8&3&9&7\\\\4&7&3&9\\\\1&1&1&5\\\\1&3&2&2\\\\ \\end{matrix}\\right) \\)\\(;\\quad\\)\\( RE = \\left(\\begin{matrix}71&70&73&115\\\\74&59&86&96\\\\51&74&52&94\\\\90&67&105&107\\\\ \\end{matrix}\\right) \\)\\(;\\quad\\)\\( \\vec{m} = \\left(\\begin{matrix}4\\\\1\\\\9\\\\1\\\\ \\end{matrix}\\right) \\)\\(;\\quad\\)\\( \\vec{k_R} = \\left(\\begin{matrix}4&1&5&1\\\\ \\end{matrix}\\right) \\)\\(;\\quad\\)\\( \\vec{k_Z} = \\left(\\begin{matrix}3&8&9&6\\\\ \\end{matrix}\\right) \\)\\(;\\quad\\)\\( \\vec{k_E} = \\left(\\begin{matrix}8&8&4&3\\\\ \\end{matrix}\\right) \\)\\(;\\quad\\)\\( K_{fix}=4100\\)\\(;\\quad\\)\\( \\vec{p} = \\left(\\begin{matrix}987&1513&1024&1640\\\\ \\end{matrix}\\right) \\)",
"fragen":[
"Berechnen Sie den Vektor der variablen Stückkosten \\( \\vec{k_v} = \\left(\\begin{matrix}a&b&c&d\\\\ \\end{matrix}\\right) \\).",
"Berechnen Sie den Vektor der Stückdeckungsbeiträge \\( \\vec{db} = \\left(\\begin{matrix}a&b&c&d\\\\ \\end{matrix}\\right) \\).",
"Berechnen Sie die Rohstoffkosten.",
"Berechnen Sie die Fertigungskosten der ersten Produktionsstufe.",
"Berechnen Sie die Fertigungskosten der zweiten Produktionsstufe.",
"Berechnen Sie die gesamten Kosten.",
"Berechnen Sie den Erlös.",
"Berechnen Sie den Deckungsbeitrag.",
"Berechnen Sie den Gewinn."
],
"antworten":[
"\\( a= \\){1:NUMERICAL:=782:0}\\( b= \\){1:NUMERICAL:=876:0}\\( c= \\){1:NUMERICAL:=819:0}\\( d= \\){1:NUMERICAL:=1286:0}<br>",
"\\( a= \\){1:NUMERICAL:=205:0}\\( b= \\){1:NUMERICAL:=637:0}\\( c= \\){1:NUMERICAL:=205:0}\\( d= \\){1:NUMERICAL:=354:0}<br>",
"{1:NUMERICAL:=11408:0}",
"{1:NUMERICAL:=1174:0}",
"{1:NUMERICAL:=79:0}",
"{1:NUMERICAL:=16761:0}",
"{1:NUMERICAL:=16317:0}",
"{1:NUMERICAL:=3656:0}",
"{1:NUMERICAL:=-444:0}"
]
},
{
"einleitung":"Gegeben:</p> <p>\\( RZ = \\left(\\begin{matrix}4&5\\\\1&7\\\\ \\end{matrix}\\right) \\)\\(;\\quad\\)\\( ZE = \\left(\\begin{matrix}7&1&7&7\\\\6&9&8&9\\\\ \\end{matrix}\\right) \\)\\(;\\quad\\)\\( RE = \\left(\\begin{matrix}58&49&68&73\\\\49&64&63&70\\\\ \\end{matrix}\\right) \\)\\(;\\quad\\)\\( \\vec{m} = \\left(\\begin{matrix}9\\\\7\\\\5\\\\2\\\\ \\end{matrix}\\right) \\)\\(;\\quad\\)\\( \\vec{k_R} = \\left(\\begin{matrix}8&6\\\\ \\end{matrix}\\right) \\)\\(;\\quad\\)\\( \\vec{k_Z} = \\left(\\begin{matrix}6&9\\\\ \\end{matrix}\\right) \\)\\(;\\quad\\)\\( \\vec{k_E} = \\left(\\begin{matrix}8&9&4&2\\\\ \\end{matrix}\\right) \\)\\(;\\quad\\)\\( K_{fix}=5100\\)\\(;\\quad\\)\\( \\vec{p} = \\left(\\begin{matrix}781&563&1295&1384\\\\ \\end{matrix}\\right) \\)",
"fragen":[
"Berechnen Sie den Vektor der variablen Stückkosten \\( \\vec{k_v} = \\left(\\begin{matrix}a&b&c&d\\\\ \\end{matrix}\\right) \\).",
"Berechnen Sie den Vektor der Stückdeckungsbeiträge \\( \\vec{db} = \\left(\\begin{matrix}a&b&c&d\\\\ \\end{matrix}\\right) \\).",
"Berechnen Sie die Rohstoffkosten.",
"Berechnen Sie die Fertigungskosten der ersten Produktionsstufe.",
"Berechnen Sie die Fertigungskosten der zweiten Produktionsstufe.",
"Berechnen Sie die gesamten Kosten.",
"Berechnen Sie den Erlös.",
"Berechnen Sie den Deckungsbeitrag.",
"Berechnen Sie den Gewinn."
],
"antworten":[
"\\( a= \\){1:NUMERICAL:=862:0}\\( b= \\){1:NUMERICAL:=872:0}\\( c= \\){1:NUMERICAL:=1040:0}\\( d= \\){1:NUMERICAL:=1129:0}<br>",
"\\( a= \\){1:NUMERICAL:=-81:0}\\( b= \\){1:NUMERICAL:=-309:0}\\( c= \\){1:NUMERICAL:=255:0}\\( d= \\){1:NUMERICAL:=255:0}<br>",
"{1:NUMERICAL:=18872:0}",
"{1:NUMERICAL:=2289:0}",
"{1:NUMERICAL:=159:0}",
"{1:NUMERICAL:=26420:0}",
"{1:NUMERICAL:=20213:0}",
"{1:NUMERICAL:=-1107:0}",
"{1:NUMERICAL:=-6207:0}"
]
},
{
"einleitung":"Gegeben:</p> <p>\\( RZ = \\left(\\begin{matrix}6&7\\\\1&3\\\\ \\end{matrix}\\right) \\)\\(;\\quad\\)\\( ZE = \\left(\\begin{matrix}4&4&7\\\\9&2&2\\\\ \\end{matrix}\\right) \\)\\(;\\quad\\)\\( RE = \\left(\\begin{matrix}87&38&56\\\\31&10&13\\\\ \\end{matrix}\\right) \\)\\(;\\quad\\)\\( \\vec{m} = \\left(\\begin{matrix}4\\\\6\\\\2\\\\ \\end{matrix}\\right) \\)\\(;\\quad\\)\\( \\vec{k_R} = \\left(\\begin{matrix}3&5\\\\ \\end{matrix}\\right) \\)\\(;\\quad\\)\\( \\vec{k_Z} = \\left(\\begin{matrix}4&2\\\\ \\end{matrix}\\right) \\)\\(;\\quad\\)\\( \\vec{k_E} = \\left(\\begin{matrix}1&7&2\\\\ \\end{matrix}\\right) \\)\\(;\\quad\\)\\( K_{fix}=820\\)\\(;\\quad\\)\\( \\vec{p} = \\left(\\begin{matrix}252&318&192\\\\ \\end{matrix}\\right) \\)",
"fragen":[
"Berechnen Sie den Vektor der variablen Stückkosten \\( \\vec{k_v} = \\left(\\begin{matrix}a&b&c\\\\ \\end{matrix}\\right) \\).",
"Berechnen Sie den Vektor der Stückdeckungsbeiträge \\( \\vec{db} = \\left(\\begin{matrix}a&b&c\\\\ \\end{matrix}\\right) \\).",
"Berechnen Sie die Rohstoffkosten.",
"Berechnen Sie die Fertigungskosten der ersten Produktionsstufe.",
"Berechnen Sie die Fertigungskosten der zweiten Produktionsstufe.",
"Berechnen Sie die gesamten Kosten.",
"Berechnen Sie den Erlös.",
"Berechnen Sie den Deckungsbeitrag.",
"Berechnen Sie den Gewinn."
],
"antworten":[
"\\( a= \\){1:NUMERICAL:=451:0}\\( b= \\){1:NUMERICAL:=191:0}\\( c= \\){1:NUMERICAL:=267:0}<br>",
"\\( a= \\){1:NUMERICAL:=-199:0}\\( b= \\){1:NUMERICAL:=127:0}\\( c= \\){1:NUMERICAL:=-75:0}<br>",
"{1:NUMERICAL:=3114:0}",
"{1:NUMERICAL:=320:0}",
"{1:NUMERICAL:=50:0}",
"{1:NUMERICAL:=4304:0}",
"{1:NUMERICAL:=3300:0}",
"{1:NUMERICAL:=-184:0}",
"{1:NUMERICAL:=-1004:0}"
]
},
{
"einleitung":"Gegeben:</p> <p>\\( RZ = \\left(\\begin{matrix}6&6\\\\1&7\\\\7&2\\\\4&7\\\\ \\end{matrix}\\right) \\)\\(;\\quad\\)\\( ZE = \\left(\\begin{matrix}8&5&9&2\\\\9&3&2&8\\\\ \\end{matrix}\\right) \\)\\(;\\quad\\)\\( RE = \\left(\\begin{matrix}102&48&66&60\\\\71&26&23&58\\\\74&41&67&30\\\\95&41&50&64\\\\ \\end{matrix}\\right) \\)\\(;\\quad\\)\\( \\vec{m} = \\left(\\begin{matrix}6\\\\4\\\\4\\\\7\\\\ \\end{matrix}\\right) \\)\\(;\\quad\\)\\( \\vec{k_R} = \\left(\\begin{matrix}5&4&8&6\\\\ \\end{matrix}\\right) \\)\\(;\\quad\\)\\( \\vec{k_Z} = \\left(\\begin{matrix}4&2\\\\ \\end{matrix}\\right) \\)\\(;\\quad\\)\\( \\vec{k_E} = \\left(\\begin{matrix}2&9&3&6\\\\ \\end{matrix}\\right) \\)\\(;\\quad\\)\\( K_{fix}=6500\\)\\(;\\quad\\)\\( \\vec{p} = \\left(\\begin{matrix}1866&1789&2276&2115\\\\ \\end{matrix}\\right) \\)",
"fragen":[
"Berechnen Sie den Vektor der variablen Stückkosten \\( \\vec{k_v} = \\left(\\begin{matrix}a&b&c&d\\\\ \\end{matrix}\\right) \\).",
"Berechnen Sie den Vektor der Stückdeckungsbeiträge \\( \\vec{db} = \\left(\\begin{matrix}a&b&c&d\\\\ \\end{matrix}\\right) \\).",
"Berechnen Sie die Rohstoffkosten.",
"Berechnen Sie die Fertigungskosten der ersten Produktionsstufe.",
"Berechnen Sie die Fertigungskosten der zweiten Produktionsstufe.",
"Berechnen Sie die gesamten Kosten.",
"Berechnen Sie den Erlös.",
"Berechnen Sie den Deckungsbeitrag.",
"Berechnen Sie den Gewinn."
],
"antworten":[
"\\( a= \\){1:NUMERICAL:=2008:0}\\( b= \\){1:NUMERICAL:=953:0}\\( c= \\){1:NUMERICAL:=1301:0}\\( d= \\){1:NUMERICAL:=1186:0}<br>",
"\\( a= \\){1:NUMERICAL:=-142:0}\\( b= \\){1:NUMERICAL:=836:0}\\( c= \\){1:NUMERICAL:=975:0}\\( d= \\){1:NUMERICAL:=929:0}<br>",
"{1:NUMERICAL:=28532:0}",
"{1:NUMERICAL:=732:0}",
"{1:NUMERICAL:=102:0}",
"{1:NUMERICAL:=35866:0}",
"{1:NUMERICAL:=42261:0}",
"{1:NUMERICAL:=12895:0}",
"{1:NUMERICAL:=6395:0}"
]
},
{
"einleitung":"Gegeben:</p> <p>\\( RZ = \\left(\\begin{matrix}2&5&6\\\\5&4&7\\\\ \\end{matrix}\\right) \\)\\(;\\quad\\)\\( ZE = \\left(\\begin{matrix}9&3&6&3\\\\1&9&5&3\\\\1&7&2&4\\\\ \\end{matrix}\\right) \\)\\(;\\quad\\)\\( RE = \\left(\\begin{matrix}29&93&49&45\\\\56&100&64&55\\\\ \\end{matrix}\\right) \\)\\(;\\quad\\)\\( \\vec{m} = \\left(\\begin{matrix}4\\\\3\\\\9\\\\5\\\\ \\end{matrix}\\right) \\)\\(;\\quad\\)\\( \\vec{k_R} = \\left(\\begin{matrix}7&9\\\\ \\end{matrix}\\right) \\)\\(;\\quad\\)\\( \\vec{k_Z} = \\left(\\begin{matrix}1&2&4\\\\ \\end{matrix}\\right) \\)\\(;\\quad\\)\\( \\vec{k_E} = \\left(\\begin{matrix}9&6&9&4\\\\ \\end{matrix}\\right) \\)\\(;\\quad\\)\\( K_{fix}=6200\\)\\(;\\quad\\)\\( \\vec{p} = \\left(\\begin{matrix}1457&1149&1262&804\\\\ \\end{matrix}\\right) \\)",
"fragen":[
"Berechnen Sie den Vektor der variablen Stückkosten \\( \\vec{k_v} = \\left(\\begin{matrix}a&b&c&d\\\\ \\end{matrix}\\right) \\).",
"Berechnen Sie den Vektor der Stückdeckungsbeiträge \\( \\vec{db} = \\left(\\begin{matrix}a&b&c&d\\\\ \\end{matrix}\\right) \\).",
"Berechnen Sie die Rohstoffkosten.",
"Berechnen Sie die Fertigungskosten der ersten Produktionsstufe.",
"Berechnen Sie die Fertigungskosten der zweiten Produktionsstufe.",
"Berechnen Sie die gesamten Kosten.",
"Berechnen Sie den Erlös.",
"Berechnen Sie den Deckungsbeitrag.",
"Berechnen Sie den Gewinn."
],
"antworten":[
"\\( a= \\){1:NUMERICAL:=731:0}\\( b= \\){1:NUMERICAL:=1606:0}\\( c= \\){1:NUMERICAL:=952:0}\\( d= \\){1:NUMERICAL:=839:0}<br>",
"\\( a= \\){1:NUMERICAL:=726:0}\\( b= \\){1:NUMERICAL:=-457:0}\\( c= \\){1:NUMERICAL:=310:0}\\( d= \\){1:NUMERICAL:=-35:0}<br>",
"{1:NUMERICAL:=19802:0}",
"{1:NUMERICAL:=548:0}",
"{1:NUMERICAL:=155:0}",
"{1:NUMERICAL:=26705:0}",
"{1:NUMERICAL:=24653:0}",
"{1:NUMERICAL:=4148:0}",
"{1:NUMERICAL:=-2052:0}"
]
},
{
"einleitung":"Gegeben:</p> <p>\\( RZ = \\left(\\begin{matrix}7&5&8&1\\\\7&5&6&4\\\\3&8&3&1\\\\ \\end{matrix}\\right) \\)\\(;\\quad\\)\\( ZE = \\left(\\begin{matrix}6&3&6&9\\\\9&4&9&8\\\\4&9&8&9\\\\2&9&5&7\\\\ \\end{matrix}\\right) \\)\\(;\\quad\\)\\( RE = \\left(\\begin{matrix}121&122&156&182\\\\119&131&155&185\\\\104&77&119&125\\\\ \\end{matrix}\\right) \\)\\(;\\quad\\)\\( \\vec{m} = \\left(\\begin{matrix}7\\\\4\\\\5\\\\6\\\\ \\end{matrix}\\right) \\)\\(;\\quad\\)\\( \\vec{k_R} = \\left(\\begin{matrix}3&4&7\\\\ \\end{matrix}\\right) \\)\\(;\\quad\\)\\( \\vec{k_Z} = \\left(\\begin{matrix}5&1&2&2\\\\ \\end{matrix}\\right) \\)\\(;\\quad\\)\\( \\vec{k_E} = \\left(\\begin{matrix}2&8&4&5\\\\ \\end{matrix}\\right) \\)\\(;\\quad\\)\\( K_{fix}=8800\\)\\(;\\quad\\)\\( \\vec{p} = \\left(\\begin{matrix}2266&1738&3402&2421\\\\ \\end{matrix}\\right) \\)",
"fragen":[
"Berechnen Sie den Vektor der variablen Stückkosten \\( \\vec{k_v} = \\left(\\begin{matrix}a&b&c&d\\\\ \\end{matrix}\\right) \\).",
"Berechnen Sie den Vektor der Stückdeckungsbeiträge \\( \\vec{db} = \\left(\\begin{matrix}a&b&c&d\\\\ \\end{matrix}\\right) \\).",
"Berechnen Sie die Rohstoffkosten.",
"Berechnen Sie die Fertigungskosten der ersten Produktionsstufe.",
"Berechnen Sie die Fertigungskosten der zweiten Produktionsstufe.",
"Berechnen Sie die gesamten Kosten.",
"Berechnen Sie den Erlös.",
"Berechnen Sie den Deckungsbeitrag.",
"Berechnen Sie den Gewinn."
],
"antworten":[
"\\( a= \\){1:NUMERICAL:=1620:0}\\( b= \\){1:NUMERICAL:=1492:0}\\( c= \\){1:NUMERICAL:=1990:0}\\( d= \\){1:NUMERICAL:=2251:0}<br>",
"\\( a= \\){1:NUMERICAL:=646:0}\\( b= \\){1:NUMERICAL:=246:0}\\( c= \\){1:NUMERICAL:=1412:0}\\( d= \\){1:NUMERICAL:=170:0}<br>",
"{1:NUMERICAL:=39256:0}",
"{1:NUMERICAL:=1412:0}",
"{1:NUMERICAL:=96:0}",
"{1:NUMERICAL:=49564:0}",
"{1:NUMERICAL:=54350:0}",
"{1:NUMERICAL:=13586:0}",
"{1:NUMERICAL:=4786:0}"
]
},
{
"einleitung":"Gegeben:</p> <p>\\( RZ = \\left(\\begin{matrix}6&5&2&4\\\\8&6&3&8\\\\9&8&4&4\\\\ \\end{matrix}\\right) \\)\\(;\\quad\\)\\( ZE = \\left(\\begin{matrix}2&3\\\\1&9\\\\6&6\\\\8&9\\\\ \\end{matrix}\\right) \\)\\(;\\quad\\)\\( RE = \\left(\\begin{matrix}61&111\\\\104&168\\\\82&159\\\\ \\end{matrix}\\right) \\)\\(;\\quad\\)\\( \\vec{m} = \\left(\\begin{matrix}4\\\\8\\\\ \\end{matrix}\\right) \\)\\(;\\quad\\)\\( \\vec{k_R} = \\left(\\begin{matrix}1&5&8\\\\ \\end{matrix}\\right) \\)\\(;\\quad\\)\\( \\vec{k_Z} = \\left(\\begin{matrix}6&8&4&4\\\\ \\end{matrix}\\right) \\)\\(;\\quad\\)\\( \\vec{k_E} = \\left(\\begin{matrix}2&2\\\\ \\end{matrix}\\right) \\)\\(;\\quad\\)\\( K_{fix}=4100\\)\\(;\\quad\\)\\( \\vec{p} = \\left(\\begin{matrix}1380&2785\\\\ \\end{matrix}\\right) \\)",
"fragen":[
"Berechnen Sie den Vektor der variablen Stückkosten \\( \\vec{k_v} = \\left(\\begin{matrix}a&b\\\\ \\end{matrix}\\right) \\).",
"Berechnen Sie den Vektor der Stückdeckungsbeiträge \\( \\vec{db} = \\left(\\begin{matrix}a&b\\\\ \\end{matrix}\\right) \\).",
"Berechnen Sie die Rohstoffkosten.",
"Berechnen Sie die Fertigungskosten der ersten Produktionsstufe.",
"Berechnen Sie die Fertigungskosten der zweiten Produktionsstufe.",
"Berechnen Sie die gesamten Kosten.",
"Berechnen Sie den Erlös.",
"Berechnen Sie den Deckungsbeitrag.",
"Berechnen Sie den Gewinn."
],
"antworten":[
"\\( a= \\){1:NUMERICAL:=1315:0}\\( b= \\){1:NUMERICAL:=2375:0}<br>",
"\\( a= \\){1:NUMERICAL:=65:0}\\( b= \\){1:NUMERICAL:=410:0}<br>",
"{1:NUMERICAL:=22732:0}",
"{1:NUMERICAL:=1504:0}",
"{1:NUMERICAL:=24:0}",
"{1:NUMERICAL:=28360:0}",
"{1:NUMERICAL:=27800:0}",
"{1:NUMERICAL:=3540:0}",
"{1:NUMERICAL:=-560:0}"
]
},
{
"einleitung":"Gegeben:</p> <p>\\( RZ = \\left(\\begin{matrix}6&6&4\\\\9&4&7\\\\ \\end{matrix}\\right) \\)\\(;\\quad\\)\\( ZE = \\left(\\begin{matrix}5&1&9\\\\2&4&8\\\\3&5&4\\\\ \\end{matrix}\\right) \\)\\(;\\quad\\)\\( RE = \\left(\\begin{matrix}54&50&118\\\\74&60&141\\\\ \\end{matrix}\\right) \\)\\(;\\quad\\)\\( \\vec{m} = \\left(\\begin{matrix}5\\\\5\\\\5\\\\ \\end{matrix}\\right) \\)\\(;\\quad\\)\\( \\vec{k_R} = \\left(\\begin{matrix}2&5\\\\ \\end{matrix}\\right) \\)\\(;\\quad\\)\\( \\vec{k_Z} = \\left(\\begin{matrix}2&5&9\\\\ \\end{matrix}\\right) \\)\\(;\\quad\\)\\( \\vec{k_E} = \\left(\\begin{matrix}3&4&4\\\\ \\end{matrix}\\right) \\)\\(;\\quad\\)\\( K_{fix}=1600\\)\\(;\\quad\\)\\( \\vec{p} = \\left(\\begin{matrix}697&692&572\\\\ \\end{matrix}\\right) \\)",
"fragen":[
"Berechnen Sie den Vektor der variablen Stückkosten \\( \\vec{k_v} = \\left(\\begin{matrix}a&b&c\\\\ \\end{matrix}\\right) \\).",
"Berechnen Sie den Vektor der Stückdeckungsbeiträge \\( \\vec{db} = \\left(\\begin{matrix}a&b&c\\\\ \\end{matrix}\\right) \\).",
"Berechnen Sie die Rohstoffkosten.",
"Berechnen Sie die Fertigungskosten der ersten Produktionsstufe.",
"Berechnen Sie die Fertigungskosten der zweiten Produktionsstufe.",
"Berechnen Sie die gesamten Kosten.",
"Berechnen Sie den Erlös.",
"Berechnen Sie den Deckungsbeitrag.",
"Berechnen Sie den Gewinn."
],
"antworten":[
"\\( a= \\){1:NUMERICAL:=528:0}\\( b= \\){1:NUMERICAL:=471:0}\\( c= \\){1:NUMERICAL:=1039:0}<br>",
"\\( a= \\){1:NUMERICAL:=169:0}\\( b= \\){1:NUMERICAL:=221:0}\\( c= \\){1:NUMERICAL:=-467:0}<br>",
"{1:NUMERICAL:=9095:0}",
"{1:NUMERICAL:=1040:0}",
"{1:NUMERICAL:=55:0}",
"{1:NUMERICAL:=11790:0}",
"{1:NUMERICAL:=9805:0}",
"{1:NUMERICAL:=-385:0}",
"{1:NUMERICAL:=-1985:0}"
]
}
]
